<?xml version="1.0" encoding="UTF-8" standalone="yes"?><imgdir name="01082553.img"><imgdir name="info"><canvas name="icon" width="27" height="30"><vector name="origin" x="-3" y="29"/><string name="_hash" value="a0fe375904aae411a5fb6d9aaa1ae2375ed980b0485109365180074e4b36c6ff"/></canvas><canvas name="iconRaw" width="24" height="26"><vector name="origin" x="-3" y="29"/><string name="_hash" value="f9738f5b979351c9c2d70731133a2be2819e046ff78495a3976e866a69489f66"/></canvas><string name="islot" value="Gv"/><string name="vslot" value="GlGw"/><int name="reqJob" value="0"/><int name="reqLevel" value="0"/><int name="reqSTR" value="0"/><int name="reqDEX" value="0"/><int name="reqINT" value="0"/><int name="reqLUK" value="0"/><int name="cash" value="1"/><int name="incPAD" value="10"/><int name="incMAD" value="10"/></imgdir><imgdir name="walk1"><imgdir name="0"><canvas name="lGlove" width="10" height="10"><vector name="origin" x="13" y="3"/><imgdir name="map"><vector name="navel" x="0" y="0"/></imgdir><string name="z" value="gloveOverBody"/><string name="_hash" value="8075bde0d47d063918e466cba328666d5000b02501a19fc5d52e82ddbb5796f3"/></canvas><canvas name="rGlove" width="9" height="11"><vector name="origin" x="-9" y="4"/><imgdir name="map"><vector name="navel" x="0" y="0"/></imgdir><string name="z" value="glove"/><string name="_hash" value="a8a74e02e0054b9b68fa759d8739e1a4fc93164a905ade32a08207431102adbd"/></canvas></imgdir><imgdir name="1"><canvas name="lGlove" width="5" height="8"><vector name="origin" x="8" y="1"/><imgdir name="map"><vector name="navel" x="0" y="0"/></imgdir><string name="z" value="gloveOverBody"/><string name="_hash" value="00735f53221c53604caf5c076b06a24cf0056e65dd9b13e9b6767ecc88445d7a"/></canvas><canvas name="rGlove" width="11" height="9"><vector name="origin" x="0" y="0"/><imgdir name="map"><vector name="navel" x="0" y="0"/></imgdir><string name="z" value="glove"/><string name="_hash" value="1f2ceb5eab4985f1bc689e232ebf31def2177e61f7838c40b5642ab6fe1f87ec"/></canvas></imgdir><imgdir name="2"><canvas name="lGlove" width="10" height="10"><vector name="origin" x="13" y="3"/><imgdir name="map"><vector name="navel" x="0" y="0"/></imgdir><string name="z" value="gloveOverBody"/><string name="_hash" value="a9110ad582ed551a3bd4eb17307f5679393edaac1bad229db8a62319af781299"/></canvas><uol name="rGlove" value="../0/rGlove"/></imgdir><imgdir name="3"><canvas name="lGlove" width="10" height="10"><vector name="origin" x="15" y="9"/><imgdir name="map"><vector name="navel" x="0" y="0"/></imgdir><string name="z" value="gloveOverBody"/><string name="_hash" value="ef2942cd28f780c89a6523ca693ba9419000d36e405b122e4e6ce0dc3c8a1be1"/></canvas><canvas name="rGlove" width="9" height="11"><vector name="origin" x="-11" y="7"/><imgdir name="map"><vector name="navel" x="0" y="0"/></imgdir><string name="z" value="glove"/><string name="_hash" value="e93c58dc909bdfc5e0fe53eba513960e739960c60861ebaa3054f853d7652ac3"/></canvas></imgdir></imgdir><imgdir name="walk2"><imgdir name="0"><canvas name="lGlove" width="8" height="11"><vector name="origin" x="10" y="1"/><imgdir name="map"><vector name="navel" x="0" y="0"/></imgdir><string name="z" value="gloveOverHair"/><string name="_hash" value="cef0f21dda53229b33cac73ccaac4690c64346792db5f7e6b083cbcf8a121b3a"/></canvas><canvas name="rGlove" width="11" height="11"><vector name="origin" x="0" y="6"/><imgdir name="map"><vector name="navel" x="0" y="0"/></imgdir><string name="z" value="gloveOverHair"/><string name="_hash" value="715662238ac854bb37c849ab705733d05dbe99af5770bf004c055c6be70e21d4"/></canvas></imgdir><imgdir name="1"><canvas name="lGlove" width="8" height="11"><vector name="origin" x="11" y="0"/><imgdir name="map"><vector name="navel" x="0" y="0"/></imgdir><string name="z" value="gloveOverHair"/><string name="_hash" value="76daddccb1b948cf33de1a1c3db02c0b983c3a39a222c2902c448ad105f91ef1"/></canvas><canvas name="rGlove" width="12" height="11"><vector name="origin" x="2" y="5"/><imgdir name="map"><vector name="navel" x="0" y="0"/></imgdir><string name="z" value="gloveOverHair"/><string name="_hash" value="9f4481d320aa95ac32ac4c587d4cc587f8287bb4fdfb17a784c1ef9e1b22f6a7"/></canvas></imgdir><imgdir name="2"><uol name="lGlove" value="../0/lGlove"/><uol name="rGlove" value="../0/rGlove"/></imgdir><imgdir name="3"><canvas name="lGlove" width="8" height="11"><vector name="origin" x="9" y="3"/><imgdir name="map"><vector name="navel" x="0" y="0"/></imgdir><string name="z" value="gloveOverHair"/><string name="_hash" value="6d260bfdcb633d5a912e9408431da1ffc9f714c7978d7d613f3fb3b0c91f0e4f"/></canvas><canvas name="rGlove" width="1" height="1"><vector name="origin" x="-1" y="7"/><imgdir name="map"><vector name="navel" x="0" y="0"/></imgdir><string name="z" value="gloveOverHair"/><string name="_inlink" value="walk2/0/rGlove"/></canvas></imgdir></imgdir><imgdir name="stand1"><imgdir name="0"><canvas name="lGlove" width="7" height="10"><vector name="origin" x="8" y="0"/><imgdir name="map"><vector name="navel" x="0" y="0"/></imgdir><string name="z" value="gloveOverBody"/><string name="_hash" value="2d6efb2deaed06a4024da263d7d7469fe28ec0cbba88cf7c494ae11489beb77d"/></canvas><canvas name="rGlove" width="10" height="12"><vector name="origin" x="-8" y="1"/><imgdir name="map"><vector name="navel" x="0" y="0"/></imgdir><string name="z" value="glove"/><string name="_hash" value="70716c3236986930ded31b32512c709786fb2c210ebaaa28e688e0104b1b0b67"/></canvas></imgdir><imgdir name="1"><canvas name="lGlove" width="8" height="11"><vector name="origin" x="10" y="1"/><imgdir name="map"><vector name="navel" x="0" y="0"/></imgdir><string name="z" value="gloveOverBody"/><string name="_hash" value="c77eccecca039fd057ae5fd6170e014546ac458c90333ccf10fb6e7b195e89c5"/></canvas><canvas name="rGlove" width="10" height="12"><vector name="origin" x="-8" y="2"/><imgdir name="map"><vector name="navel" x="0" y="0"/></imgdir><string name="z" value="glove"/><string name="_hash" value="f6868cb4a8fb477b8a7d96e188721eddf6a49631a0b95589901bf4af0cfda59b"/></canvas></imgdir><imgdir name="2"><canvas name="lGlove" width="9" height="11"><vector name="origin" x="12" y="0"/><imgdir name="map"><vector name="navel" x="0" y="0"/></imgdir><string name="z" value="gloveOverBody"/><string name="_hash" value="31db84ff2429530c1ff54c8b95b30d12af24fd81f59fa39b93c9348c6db2f16f"/></canvas><canvas name="rGlove" width="10" height="12"><vector name="origin" x="-8" y="1"/><imgdir name="map"><vector name="navel" x="0" y="0"/></imgdir><string name="z" value="glove"/><string name="_hash" value="5031711e39162379c06ab83b83876bda7c446f09ddc2be6a998b5e2f22f404e6"/></canvas></imgdir></imgdir><imgdir name="stand2"><imgdir name="0"><canvas name="lGlove" width="8" height="9"><vector name="origin" x="10" y="-2"/><imgdir name="map"><vector name="navel" x="0" y="0"/></imgdir><string name="z" value="gloveOverHair"/><string name="_hash" value="669f87149f6ba3463519cf2ac1ac7299770eb73fc9ba8d03c9aee3e8c504dbbe"/></canvas><canvas name="rGlove" width="11" height="11"><vector name="origin" x="0" y="5"/><imgdir name="map"><vector name="navel" x="0" y="0"/></imgdir><string name="z" value="gloveOverHair"/><string name="_hash" value="b8525f4f56cf17a494d5b6517289e363fc6d7846bb3c1795c1722fa2c58f5de8"/></canvas></imgdir><imgdir name="1"><canvas name="lGlove" width="1" height="1"><vector name="origin" x="10" y="-1"/><imgdir name="map"><vector name="navel" x="0" y="0"/></imgdir><string name="z" value="gloveOverHair"/><string name="_inlink" value="stand2/0/lGlove"/></canvas><canvas name="rGlove" width="11" height="11"><vector name="origin" x="0" y="6"/><imgdir name="map"><vector name="navel" x="0" y="0"/></imgdir><string name="z" value="gloveOverHair"/><string name="_hash" value="80d1b2f8f1fe149ae3e0e5fc909e5fedc718df056d6d7ee5bb5a2b93f970ae9b"/></canvas></imgdir><imgdir name="2"><canvas name="lGlove" width="1" height="1"><vector name="origin" x="10" y="-2"/><imgdir name="map"><vector name="navel" x="0" y="0"/></imgdir><string name="z" value="gloveOverHair"/><string name="_inlink" value="stand2/0/lGlove"/></canvas><canvas name="rGlove" width="1" height="1"><vector name="origin" x="0" y="5"/><imgdir name="map"><vector name="navel" x="0" y="0"/></imgdir><string name="z" value="gloveOverHair"/><string name="_inlink" value="stand2/1/rGlove"/></canvas></imgdir></imgdir><imgdir name="alert"><imgdir name="0"><canvas name="lGlove" width="8" height="9"><vector name="origin" x="12" y="6"/><imgdir name="map"><vector name="navel" x="0" y="0"/></imgdir><string name="z" value="gloveBelowWeapon"/><string name="_hash" value="ad552a0c7567975cbf98f562c7ccbfc512afba86e87c72523bce4c6d8e60124d"/></canvas><canvas name="rGlove" width="11" height="9"><vector name="origin" x="0" y="2"/><imgdir name="map"><vector name="navel" x="0" y="0"/></imgdir><string name="z" value="gloveOverHair"/><string name="_hash" value="05c710ff4cb5154c71e3c4c25046d1a3ece33b412ba8eec4cbc3fb6003b6e8e4"/></canvas></imgdir><imgdir name="1"><canvas name="lGlove" width="8" height="9"><vector name="origin" x="12" y="4"/><imgdir name="map"><vector name="navel" x="0" y="0"/></imgdir><string name="z" value="gloveBelowWeapon"/><string name="_hash" value="612510bc761302151d5f3e30a956885fc6e578f0ea8910d2d3526f920fb53d73"/></canvas><canvas name="rGlove" width="10" height="10"><vector name="origin" x="0" y="1"/><imgdir name="map"><vector name="navel" x="0" y="0"/></imgdir><string name="z" value="gloveOverHair"/><string name="_hash" value="f29b390520def278c78f0b0fccf35ca0aa0aff9a4abad9488a56ac2ca7d13757"/></canvas></imgdir><imgdir name="2"><canvas name="lGlove" width="1" height="1"><vector name="origin" x="12" y="2"/><imgdir name="map"><vector name="navel" x="0" y="0"/></imgdir><string name="z" value="gloveBelowWeapon"/><string name="_inlink" value="alert/1/lGlove"/></canvas><canvas name="rGlove" width="1" height="1"><vector name="origin" x="0" y="-1"/><imgdir name="map"><vector name="navel" x="0" y="0"/></imgdir><string name="z" value="gloveOverHair"/><string name="_inlink" value="alert/1/rGlove"/></canvas></imgdir></imgdir><imgdir name="swingO1"><imgdir name="1"><canvas name="lGlove" width="8" height="8"><vector name="origin" x="-8" y="6"/><imgdir name="map"><vector name="navel" x="0" y="0"/></imgdir><string name="z" value="gloveOverBody"/><string name="_hash" value="f4460049d6f8b4a23b2a0b4055dfeb6bd31cad44cbf5b6d7fc9085f1f764db75"/></canvas><canvas name="rGlove" width="9" height="10"><vector name="origin" x="12" y="6"/><imgdir name="map"><vector name="navel" x="0" y="0"/></imgdir><string name="z" value="gloveOverHair"/><string name="_hash" value="1060f4cf30152115fd1426b93a2e66ce0202bd74110d2908922e75c84ca30a08"/></canvas></imgdir><imgdir name="2"><canvas name="lGlove" width="5" height="7"><vector name="origin" x="9" y="8"/><imgdir name="map"><vector name="navel" x="0" y="0"/></imgdir><string name="z" value="gloveOverBody"/></canvas><canvas name="rGlove" width="13" height="11"><vector name="origin" x="-11" y="25"/><imgdir name="map"><vector name="navel" x="0" y="0"/></imgdir><string name="z" value="gloveOverHair"/><string name="_hash" value="12d6bfc40a1313ecb3770d1ed96f4ab21521d04aef34d2e9945e97c42511ecc8"/></canvas></imgdir></imgdir><imgdir name="swingO2"><imgdir name="0"><canvas name="lGlove" width="8" height="9"><vector name="origin" x="12" y="3"/><imgdir name="map"><vector name="navel" x="0" y="0"/></imgdir><string name="z" value="gloveOverBody"/><string name="_hash" value="6a877956fed09e854da1b7b7a67e26b26b3b68b9df8e6e0674b953ccb8662800"/></canvas><canvas name="rGlove" width="10" height="10"><vector name="origin" x="22" y="19"/><imgdir name="map"><vector name="navel" x="0" y="0"/></imgdir><string name="z" value="gloveBelowHead"/><string name="_hash" value="0e5c579e9580c6f830e170ea0dad10ec60d64fdf8781fe425971a07ecc599d44"/></canvas></imgdir><imgdir name="1"><canvas name="lGlove" width="8" height="8"><vector name="origin" x="11" y="13"/><imgdir name="map"><vector name="navel" x="0" y="0"/></imgdir><string name="z" value="gloveOverBody"/><string name="_hash" value="a9c253f5221434f17ff5595b0904f02f42e813a9b14db808d0ffdf603edc6e40"/></canvas><canvas name="rGlove" width="11" height="11"><vector name="origin" x="25" y="15"/><imgdir name="map"><vector name="navel" x="0" y="0"/></imgdir><string name="z" value="gloveBelowHead"/><string name="_hash" value="f9a8c1627a5a33f94108e426c65229a093cdef4371b838fdc80f1465e3822fa1"/></canvas></imgdir><imgdir name="2"><canvas name="lGlove" width="8" height="7"><vector name="origin" x="19" y="13"/><imgdir name="map"><vector name="navel" x="0" y="0"/></imgdir><string name="z" value="gloveOverBody"/><string name="_hash" value="345aec105dca80c7aa2091dd07cc3dd1eeacb8a62dc5140c5ef513bf94b7cd60"/></canvas><canvas name="rGlove" width="11" height="10"><vector name="origin" x="-12" y="5"/><imgdir name="map"><vector name="navel" x="0" y="0"/></imgdir><string name="z" value="glove"/><string name="_hash" value="353466b1cb245d524d4e8fb1cf121c62b51704529b9a7cee94ba35f4183bedb3"/></canvas></imgdir></imgdir><imgdir name="swingO3"><imgdir name="0"><canvas name="lGlove" width="14" height="8"><vector name="origin" x="28" y="9"/><imgdir name="map"><vector name="navel" x="0" y="0"/></imgdir><string name="z" value="gloveOverBody"/><string name="_hash" value="12f3b2515b064f96eeea56d3746906cd765d660e5e2d7b798644f5502e7bce0f"/></canvas><canvas name="rGlove" width="12" height="11"><vector name="origin" x="-12" y="17"/><imgdir name="map"><vector name="navel" x="0" y="0"/></imgdir><string name="z" value="glove"/><string name="_hash" value="dd35942cc090fc1b82a410c6c4af38ad6cd185e796a1fc03074c0332d83dec25"/></canvas></imgdir><imgdir name="1"><canvas name="rGlove" width="12" height="10"><vector name="origin" x="23" y="8"/><imgdir name="map"><vector name="navel" x="0" y="0"/></imgdir><string name="z" value="gloveBelowHead"/><string name="_hash" value="eced37eeffe03901cf103a3177518fca8381dd3a57c7b7577ae7e24c2cf59b69"/></canvas></imgdir></imgdir><imgdir name="swingOF"><imgdir name="0"><canvas name="lGlove" width="9" height="9"><vector name="origin" x="15" y="3"/><imgdir name="map"><vector name="navel" x="0" y="0"/></imgdir><string name="z" value="glove"/><string name="_hash" value="62f306fdb7a0e9658d046f0a6e8b2ee97757f4f130504d266f4f3153a1049966"/></canvas><canvas name="rGlove" width="11" height="10"><vector name="origin" x="-12" y="13"/><imgdir name="map"><vector name="navel" x="0" y="0"/></imgdir><string name="z" value="gloveOverHair"/><string name="_hash" value="c82921489a50d2963802958bc13d74aa9e344ae7ed3c34ce704027faccc7fde0"/></canvas></imgdir><imgdir name="3"><canvas name="lGlove" width="12" height="7"><vector name="origin" x="19" y="-5"/><imgdir name="map"><vector name="navel" x="0" y="0"/></imgdir><string name="z" value="glove"/><string name="_hash" value="b8c3f111ad61b2b018cd5b4f393ba8445bb5313110aab64b841e20c43bedc19d"/></canvas><canvas name="rGlove" width="11" height="8"><vector name="origin" x="-12" y="20"/><imgdir name="map"><vector name="navel" x="0" y="0"/></imgdir><string name="z" value="gloveOverBody"/><string name="_hash" value="c10e6b41fc9510bb7f94cb468a44573cb249ce884eb7482d5995b93a9b1239e6"/></canvas></imgdir></imgdir><imgdir name="swingT1"><imgdir name="0"><canvas name="lGlove" width="13" height="13"><vector name="origin" x="-1" y="27"/><imgdir name="map"><vector name="navel" x="0" y="0"/></imgdir><string name="z" value="gloveOverHair"/><string name="_hash" value="bfe8d2a8523310fbaf0f5b0aa07e30c83fd68302fa7cfc44161aa87d02a30711"/></canvas><canvas name="rGlove" width="11" height="12"><vector name="origin" x="-13" y="30"/><imgdir name="map"><vector name="navel" x="0" y="0"/></imgdir><string name="z" value="gloveOverHair"/><string name="_hash" value="92134074b803982c3732d33995da143c4d9f0d831b11f5cee1f469e03177ea5a"/></canvas></imgdir><imgdir name="1"><canvas name="lGlove" width="10" height="10"><vector name="origin" x="23" y="16"/><imgdir name="map"><vector name="navel" x="0" y="0"/></imgdir><string name="z" value="gloveOverHair"/><string name="_hash" value="ab01fefc50998f7639f2d57edc1f15004c4d74a10a718edf3a9630fceef794f9"/></canvas><canvas name="rGlove" width="12" height="13"><vector name="origin" x="19" y="25"/><imgdir name="map"><vector name="navel" x="0" y="0"/></imgdir><string name="z" value="gloveOverHair"/><string name="_hash" value="c1f31c64520fb4c7dbe6cd6b501497175821f4f015fd89a979bdb272988ec166"/></canvas></imgdir><imgdir name="2"><canvas name="rGlove" width="11" height="11"><vector name="origin" x="20" y="-5"/><imgdir name="map"><vector name="navel" x="0" y="0"/></imgdir><string name="z" value="glove"/><string name="_hash" value="91b8a14fee6c44483c7f76207f9c87ceaea4f2aa846aa447b9ccb60177c3b770"/></canvas><canvas name="lGlove" width="5" height="6"><vector name="origin" x="11" y="-7"/><imgdir name="map"><vector name="navel" x="0" y="0"/></imgdir><string name="z" value="gloveOverBody"/></canvas></imgdir></imgdir><imgdir name="swingT2"><imgdir name="1"><canvas name="lGlove" width="9" height="9"><vector name="origin" x="21" y="13"/><imgdir name="map"><vector name="navel" x="0" y="0"/></imgdir><string name="z" value="gloveOverBody"/><string name="_hash" value="dbefbe7a398a81ecc15cfe7e8c1aa8546fbad273859b645688bbd0b01b5d8045"/></canvas><canvas name="rGlove" width="12" height="9"><vector name="origin" x="19" y="9"/><imgdir name="map"><vector name="navel" x="0" y="0"/></imgdir><string name="z" value="glove"/><string name="_hash" value="752b2f740c9bcd2dce23200291f33138ecb8f02b6714bc504d07dd2e99bd92a8"/></canvas></imgdir><imgdir name="2"><canvas name="lGlove" width="11" height="11"><vector name="origin" x="0" y="0"/><imgdir name="map"><vector name="navel" x="0" y="0"/></imgdir><string name="z" value="glove"/><string name="_hash" value="48771fcbb1d82c1dce7b8e61e9ece4e9c3acd22e00ed3fface5c65c9d75c659d"/></canvas></imgdir></imgdir><imgdir name="swingT3"><imgdir name="0"><canvas name="lGlove" width="12" height="10"><vector name="origin" x="-1" y="3"/><imgdir name="map"><vector name="navel" x="0" y="0"/></imgdir><string name="z" value="glove"/><string name="_hash" value="25677fbc197090e0bff83024f06ec6e3ab59a497fd98d57f53facdb2289e593a"/></canvas><canvas name="rGlove" width="7" height="10"><vector name="origin" x="-10" y="3"/><imgdir name="map"><vector name="navel" x="0" y="0"/></imgdir><string name="z" value="gloveOverBody"/><string name="_hash" value="93ca2db0737a7485b4a687c08018f8d054c684b328b61c43482381fc3f01c13c"/></canvas></imgdir><imgdir name="1"><canvas name="lGlove" width="11" height="9"><vector name="origin" x="3" y="2"/><imgdir name="map"><vector name="navel" x="0" y="0"/></imgdir><string name="z" value="gloveBelowHead"/><string name="_hash" value="ea9c4f8870c2b882dd41ac463d335e1afe74ef600427a5f9d1b46877dae7e57f"/></canvas></imgdir></imgdir><imgdir name="swingTF"><imgdir name="1"><canvas name="lGlove" width="8" height="7"><vector name="origin" x="-7" y="16"/><imgdir name="map"><vector name="navel" x="0" y="0"/></imgdir><string name="z" value="gloveBelowHead"/><string name="_hash" value="9a6846f46826dfb4ae13a1c7f58005752f775b0ed6ae98a8375580a3cfea825c"/></canvas></imgdir><imgdir name="2"><canvas name="lGlove" width="11" height="14"><vector name="origin" x="16" y="27"/><imgdir name="map"><vector name="navel" x="0" y="0"/></imgdir><string name="z" value="gloveWristOverHair"/><string name="_hash" value="7d2e3968ecfb3a953f62818118cd44b4430e62c3e6994772c4f00ed58ec9cbf8"/></canvas></imgdir><imgdir name="3"><canvas name="lGlove" width="1" height="1"><vector name="origin" x="16" y="-3"/><imgdir name="map"><vector name="navel" x="0" y="0"/></imgdir><string name="z" value="gloveOverBody"/><string name="_hash" value="762078414503bfdaaf25db930dfe597eb87261b642933e8f96e4ea90ca67136c"/><string name="_outlink" value="Character/Glove/01082535.img/swingTF/3/lGlove"/></canvas><canvas name="rGlove" width="11" height="11"><vector name="origin" x="22" y="-3"/><imgdir name="map"><vector name="navel" x="0" y="0"/></imgdir><string name="z" value="gloveOverHair"/><string name="_hash" value="ee811ff5d030df9fb748dc0058703121645a1df016d7fcedf475eb98ff2496b5"/></canvas></imgdir></imgdir><imgdir name="swingP1"><imgdir name="0"><canvas name="lGlove" width="12" height="13"><vector name="origin" x="5" y="30"/><imgdir name="map"><vector name="navel" x="0" y="0"/></imgdir><string name="z" value="gloveOverHair"/><string name="_hash" value="c89ec6f62659cd21a2bf4616cab0d972d39ecb877506cdf9b00dd51c72c6f075"/></canvas><canvas name="rGlove" width="11" height="12"><vector name="origin" x="-12" y="32"/><imgdir name="map"><vector name="navel" x="0" y="0"/></imgdir><string name="z" value="gloveOverHair"/><string name="_hash" value="7dcc219f141216ac824f819106f08f71e9983b805ee7f45e7be473f45035123a"/></canvas></imgdir><imgdir name="1"><canvas name="lGlove" width="12" height="11"><vector name="origin" x="25" y="12"/><imgdir name="map"><vector name="navel" x="0" y="0"/></imgdir><string name="z" value="gloveOverHair"/><string name="_hash" value="160da0c1be7465bae5eab02cedd695daf7778115d9875fa8120e933d460f76c6"/></canvas><canvas name="rGlove" width="11" height="12"><vector name="origin" x="19" y="26"/><imgdir name="map"><vector name="navel" x="0" y="0"/></imgdir><string name="z" value="gloveOverHair"/><string name="_hash" value="8a8ab5db63ac52630a22fd035d15297055a05c08f75487914a1076eb1bacb241"/></canvas></imgdir><imgdir name="2"><canvas name="lGlove" width="4" height="7"><vector name="origin" x="10" y="-5"/><imgdir name="map"><vector name="navel" x="0" y="0"/></imgdir><string name="z" value="gloveOverBody"/></canvas><canvas name="rGlove" width="1" height="1"><vector name="origin" x="20" y="-4"/><imgdir name="map"><vector name="navel" x="0" y="0"/></imgdir><string name="z" value="glove"/><string name="_inlink" value="swingT1/2/rGlove"/></canvas></imgdir></imgdir><imgdir name="swingP2"><imgdir name="0"><canvas name="rGlove" width="11" height="13"><vector name="origin" x="22" y="18"/><imgdir name="map"><vector name="navel" x="0" y="0"/></imgdir><string name="z" value="glove"/><string name="_hash" value="71ff3ad28a187c991b200c9c22b8845c3e534f727ae3ffc03e249acf970666cf"/></canvas></imgdir><imgdir name="1"><canvas name="rGlove" width="14" height="10"><vector name="origin" x="23" y="7"/><imgdir name="map"><vector name="navel" x="0" y="0"/></imgdir><string name="z" value="glove"/><string name="_hash" value="8e1980a1641f92b0ba500efb27275813bad2b5e6379867a44389990745961c74"/></canvas></imgdir><imgdir name="2"><canvas name="lGlove" width="1" height="1"><vector name="origin" x="0" y="0"/><imgdir name="map"><vector name="navel" x="0" y="0"/></imgdir><string name="z" value="glove"/><string name="_inlink" value="swingT2/2/lGlove"/></canvas></imgdir></imgdir><imgdir name="swingPF"><imgdir name="0"><canvas name="lGlove" width="10" height="9"><vector name="origin" x="23" y="7"/><imgdir name="map"><vector name="navel" x="0" y="0"/></imgdir><string name="z" value="gloveOverHair"/><string name="_hash" value="38a2bee14c374c0d347290084cb588e53bf5d39186fb396f46f1d38f5b90204a"/></canvas><canvas name="rGlove" width="10" height="12"><vector name="origin" x="-16" y="11"/><imgdir name="map"><vector name="navel" x="0" y="0"/></imgdir><string name="z" value="glove"/><string name="_hash" value="a7f90352124b43d3bf8cc43753eeed44df44425fa99a99626673922441d08101"/></canvas></imgdir><imgdir name="1"><canvas name="lGlove" width="1" height="1"><vector name="origin" x="21" y="3"/><imgdir name="map"><vector name="navel" x="0" y="0"/></imgdir><string name="z" value="gloveOverHair"/><string name="_inlink" value="swingPF/0/lGlove"/></canvas><canvas name="rGlove" width="11" height="12"><vector name="origin" x="-15" y="14"/><imgdir name="map"><vector name="navel" x="0" y="0"/></imgdir><string name="z" value="glove"/><string name="_hash" value="3cbd1e50b8bed6dc7d3358425e46eeede662ec94c5ef518491447eb2d42ecf91"/></canvas></imgdir><imgdir name="2"><canvas name="lGlove" width="1" height="1"><vector name="origin" x="11" y="30"/><imgdir name="map"><vector name="navel" x="0" y="0"/></imgdir><string name="z" value="gloveOverHair"/><string name="_inlink" value="swingP1/0/lGlove"/></canvas><canvas name="rGlove" width="11" height="12"><vector name="origin" x="-8" y="32"/><imgdir name="map"><vector name="navel" x="0" y="0"/></imgdir><string name="z" value="gloveOverHair"/><string name="_hash" value="a204f723aef9349b25c54980aec8411ba5af7c1d9831e63db498091871c38f8f"/></canvas></imgdir><imgdir name="3"><canvas name="lGlove" width="4" height="7"><vector name="origin" x="12" y="-5"/><imgdir name="map"><vector name="navel" x="0" y="0"/></imgdir><string name="z" value="gloveOverBody"/></canvas><canvas name="rGlove" width="11" height="11"><vector name="origin" x="22" y="-4"/><imgdir name="map"><vector name="navel" x="0" y="0"/></imgdir><string name="z" value="gloveOverHair"/><string name="_hash" value="3b4d2fae75a80e1516fa790d94b78eca896bc99049075922094cd64d5c9a0ddb"/></canvas></imgdir></imgdir><imgdir name="stabO1"><imgdir name="0"><canvas name="lGlove" width="11" height="9"><vector name="origin" x="25" y="9"/><imgdir name="map"><vector name="navel" x="0" y="0"/></imgdir><string name="z" value="gloveOverBody"/><string name="_hash" value="362948e7e0c16a9ae5a33af786dbaa13d6f8061dc79447f727f9c21e467acb31"/></canvas><canvas name="rGlove" width="9" height="11"><vector name="origin" x="-10" y="4"/><imgdir name="map"><vector name="navel" x="0" y="0"/></imgdir><string name="z" value="glove"/><string name="_hash" value="3748c1af27241ecf2b4a3d2e3e5e9b17dfd4413432af35773cca1f9e77d118f0"/></canvas></imgdir><imgdir name="1"><canvas name="rGlove" width="11" height="9"><vector name="origin" x="30" y="12"/><imgdir name="map"><vector name="navel" x="0" y="0"/></imgdir><string name="z" value="gloveOverHair"/><string name="_hash" value="fe7a22418b6680604afb6aff9cc093404da14ccd6ef707aa1a1b49be676b49ea"/></canvas></imgdir></imgdir><imgdir name="stabO2"><imgdir name="0"><canvas name="lGlove" width="12" height="10"><vector name="origin" x="25" y="11"/><imgdir name="map"><vector name="navel" x="0" y="0"/></imgdir><string name="z" value="gloveOverBody"/><string name="_hash" value="ab97afb48312858523edc1b8fc45d7a4bdf0505c058701c08b7c38c7f3450f06"/></canvas><canvas name="rGlove" width="11" height="10"><vector name="origin" x="-6" y="16"/><imgdir name="map"><vector name="navel" x="0" y="0"/></imgdir><string name="z" value="gloveOverHair"/><string name="_hash" value="c71b31d73a101af9f975b475a9be1c2aeedb90f2dc9f085bfaaac3889ac03479"/></canvas></imgdir><imgdir name="1"><canvas name="rGlove" width="1" height="1"><vector name="origin" x="28" y="11"/><imgdir name="map"><vector name="navel" x="0" y="0"/></imgdir><string name="z" value="gloveOverHair"/><string name="_inlink" value="stabO1/1/rGlove"/></canvas></imgdir></imgdir><imgdir name="stabOF"><imgdir name="0"><canvas name="lGlove" width="11" height="9"><vector name="origin" x="3" y="6"/><imgdir name="map"><vector name="navel" x="0" y="0"/></imgdir><string name="z" value="gloveOverBody"/><string name="_hash" value="5484932dfffb106ea4757bc1bdadad2c80b39f1980fb5a3213d534053de104b7"/></canvas><canvas name="rGlove" width="9" height="11"><vector name="origin" x="-3" y="8"/><imgdir name="map"><vector name="navel" x="0" y="0"/></imgdir><string name="z" value="gloveBelowMailArm"/><string name="_hash" value="31bb5633d0c34b784a8961d7f219d27d5a3e307c646ddd7f46215f8ca16b46a1"/></canvas></imgdir><imgdir name="1"><canvas name="lGlove" width="11" height="10"><vector name="origin" x="35" y="13"/><imgdir name="map"><vector name="navel" x="0" y="0"/></imgdir><string name="z" value="gloveOverBody"/><string name="_hash" value="6ae5d2fd7c4ebdce8a672d8df1dfb13ad6598d3fa956a1ed9dabfca46ea35888"/></canvas><canvas name="rGlove" width="9" height="11"><vector name="origin" x="-7" y="5"/><imgdir name="map"><vector name="navel" x="0" y="0"/></imgdir><string name="z" value="gloveBelowMailArm"/><string name="_hash" value="7fb5829819517ad13bece52f1ba49132b37bcca8d2f39e2e1b81ce1bebf06bca"/></canvas></imgdir><imgdir name="2"><canvas name="lGlove" width="8" height="6"><vector name="origin" x="22" y="7"/><imgdir name="map"><vector name="navel" x="0" y="0"/></imgdir><string name="z" value="gloveOverBody"/><string name="_hash" value="d6315c6b800c1b5594fe5609d6be86a08bb60fbc6cb98a4871084a83f9547f32"/></canvas><canvas name="rGlove" width="11" height="9"><vector name="origin" x="32" y="11"/><imgdir name="map"><vector name="navel" x="0" y="0"/></imgdir><string name="z" value="gloveOverHair"/><string name="_hash" value="20e9e675eef4b5cf3f13efd6f36594e87f84abd99e31000937558cf7b480592f"/></canvas></imgdir></imgdir><imgdir name="stabT1"><imgdir name="0"><canvas name="lGlove" width="10" height="8"><vector name="origin" x="6" y="1"/><imgdir name="map"><vector name="navel" x="0" y="0"/></imgdir><string name="z" value="gloveOverHair"/><string name="_hash" value="2391c8df9187cf865d6b32d595fce0d1039ea729a6d4d4220895fbdeddff6e09"/></canvas><canvas name="rGlove" width="11" height="11"><vector name="origin" x="-14" y="9"/><imgdir name="map"><vector name="navel" x="0" y="0"/></imgdir><string name="z" value="glove"/><string name="_hash" value="ef1cf1863b302667ee0f04f7167511a0280bdd8fe64cfde5327973cf569af956"/></canvas></imgdir><imgdir name="1"><canvas name="lGlove" width="1" height="1"><vector name="origin" x="9" y="0"/><imgdir name="map"><vector name="navel" x="0" y="0"/></imgdir><string name="z" value="gloveOverHair"/><string name="_inlink" value="stabT1/0/lGlove"/></canvas><canvas name="rGlove" width="10" height="11"><vector name="origin" x="-12" y="8"/><imgdir name="map"><vector name="navel" x="0" y="0"/></imgdir><string name="z" value="glove"/><string name="_hash" value="38a8685a7616d5d5b0dc5e9d95b3099b43d4313acc4474523eb2795b087c01a3"/></canvas></imgdir><imgdir name="2"><canvas name="lGlove" width="12" height="9"><vector name="origin" x="29" y="8"/><imgdir name="map"><vector name="navel" x="0" y="0"/></imgdir><string name="z" value="gloveOverHair"/><string name="_hash" value="7630a6930a59bf7280f019a59ee5fe24dd5317d3f2dce7335b52d655af4b1fbd"/></canvas><canvas name="rGlove" width="13" height="9"><vector name="origin" x="7" y="9"/><imgdir name="map"><vector name="navel" x="0" y="0"/></imgdir><string name="z" value="glove"/><string name="_hash" value="3eb762b060d2b7a59d44c9438303a539cdcc3b945efcd3c2c326e606667ef836"/></canvas></imgdir></imgdir><imgdir name="stabT2"><imgdir name="0"><canvas name="lGlove" width="10" height="9"><vector name="origin" x="16" y="1"/><imgdir name="map"><vector name="navel" x="0" y="0"/></imgdir><string name="z" value="gloveOverHair"/><string name="_hash" value="eb7ce4bd16ec087f7d0ce79f5f01779a7244b09b6964201189b56958d5c2a8e5"/></canvas><canvas name="rGlove" width="9" height="11"><vector name="origin" x="-9" y="9"/><imgdir name="map"><vector name="navel" x="0" y="0"/></imgdir><string name="z" value="glove"/><string name="_hash" value="ad058dcb8830fc1081df77a794a9efbb66d7ac5ac2d00df107b3f99977be1ac6"/></canvas></imgdir><imgdir name="1"><canvas name="lGlove" width="11" height="10"><vector name="origin" x="19" y="2"/><imgdir name="map"><vector name="navel" x="0" y="0"/></imgdir><string name="z" value="gloveOverHair"/><string name="_hash" value="ff79c39ed5c8326beee4742e270919200ce0b34fd9f86fa8665a4de309fc7f24"/></canvas><canvas name="rGlove" width="10" height="12"><vector name="origin" x="-7" y="11"/><imgdir name="map"><vector name="navel" x="0" y="0"/></imgdir><string name="z" value="glove"/><string name="_hash" value="344f52fdb5e6fe94667204040a1b8eac14ccc180420f75d2e199be4a2ce9b515"/></canvas></imgdir><imgdir name="2"><canvas name="lGlove" width="12" height="10"><vector name="origin" x="30" y="8"/><imgdir name="map"><vector name="navel" x="0" y="0"/></imgdir><string name="z" value="gloveOverHair"/><string name="_hash" value="fcc36e83f3423f93c16fe3cfe46f1ecf834fe02c957f7aa7d8bbb5df722fbdde"/></canvas><canvas name="rGlove" width="13" height="12"><vector name="origin" x="-1" y="4"/><imgdir name="map"><vector name="navel" x="0" y="0"/></imgdir><string name="z" value="glove"/><string name="_hash" value="feaad5650807b27e6ff76382c437f2c1580d556555aba831f99f85265fed3f7f"/></canvas></imgdir></imgdir><imgdir name="stabTF"><imgdir name="0"><uol name="lGlove" value="../../swingPF/0/lGlove"/><uol name="rGlove" value="../../swingPF/0/rGlove"/></imgdir><imgdir name="1"><uol name="lGlove" value="../../swingPF/1/lGlove"/><uol name="rGlove" value="../../swingPF/1/rGlove"/></imgdir><imgdir name="2"><canvas name="lGlove" width="12" height="11"><vector name="origin" x="-17" y="16"/><imgdir name="map"><vector name="navel" x="0" y="0"/></imgdir><string name="z" value="gloveOverHair"/><string name="_hash" value="32d1cabf4146cdbf0164809f0ffd9ca18759e4b65261dd0e693d4f8388e68475"/></canvas><canvas name="rGlove" width="12" height="10"><vector name="origin" x="-5" y="7"/><imgdir name="map"><vector name="navel" x="0" y="0"/></imgdir><string name="z" value="glove"/><string name="_hash" value="ff4a5b23da14b5b187597e23fa398c02ac7ce02efd27ab03b206bb5dda71edb0"/></canvas></imgdir><imgdir name="3"><uol name="lGlove" value="../../stabT1/2/lGlove"/><uol name="rGlove" value="../../stabT1/2/rGlove"/></imgdir></imgdir><imgdir name="shoot1"><imgdir name="0"><canvas name="lGlove" width="12" height="9"><vector name="origin" x="27" y="12"/><imgdir name="map"><vector name="navel" x="0" y="0"/></imgdir><string name="z" value="gloveOverBody"/><string name="_hash" value="906e2fc2976d67e5e24bc112c64cf29439b6f0614e5d10239ebf8ba1330cc617"/></canvas><canvas name="rGlove" width="12" height="9"><vector name="origin" x="13" y="16"/><imgdir name="map"><vector name="navel" x="0" y="0"/></imgdir><string name="z" value="gloveOverHair"/><string name="_hash" value="e9f8885d51ca212ba70c619a0116a8cdf3d229f0e27f9c37571a32c8c76af32f"/></canvas></imgdir><imgdir name="1"><canvas name="lGlove" width="1" height="1"><vector name="origin" x="27" y="12"/><imgdir name="map"><vector name="navel" x="0" y="0"/></imgdir><string name="z" value="gloveOverBody"/><string name="_inlink" value="shoot1/0/lGlove"/></canvas><canvas name="rGlove" width="12" height="9"><vector name="origin" x="-1" y="16"/><imgdir name="map"><vector name="navel" x="0" y="0"/></imgdir><string name="z" value="gloveOverHair"/><string name="_hash" value="8b4d08ec2b0666cfad2c533cca4df78bd1496b524ffe5eea2cd04eb0db1cadb6"/></canvas></imgdir><imgdir name="2"><uol name="lGlove" value="../1/lGlove"/><uol name="rGlove" value="../1/rGlove"/></imgdir></imgdir><imgdir name="shoot2"><imgdir name="0"><canvas name="lGlove" width="10" height="10"><vector name="origin" x="18" y="10"/><imgdir name="map"><vector name="navel" x="0" y="0"/></imgdir><string name="z" value="gloveOverBody"/><string name="_hash" value="a0b7a7ce7c82e8e8ee894b8a485302414a58542107f883da452d7ed425095aed"/></canvas><canvas name="rGlove" width="11" height="9"><vector name="origin" x="2" y="10"/><imgdir name="map"><vector name="navel" x="0" y="0"/></imgdir><string name="z" value="gloveOverHair"/><string name="_hash" value="29a70c647b85558c2c105be6a5c3bcd570fd04bdb6a0177374acede71ca42e9a"/></canvas></imgdir><imgdir name="1"><uol name="lGlove" value="../0/lGlove"/><canvas name="rGlove" width="12" height="10"><vector name="origin" x="16" y="17"/><imgdir name="map"><vector name="navel" x="0" y="0"/></imgdir><string name="z" value="gloveOverHair"/><string name="_hash" value="e56dbfc9c7f6dd8eeeb929c0cbcd046504c94363a82682e3002a63fa38b93075"/></canvas></imgdir><imgdir name="2"><uol name="lGlove" value="../0/lGlove"/><canvas name="rGlove" width="1" height="1"><vector name="origin" x="3" y="16"/><imgdir name="map"><vector name="navel" x="0" y="0"/></imgdir><string name="z" value="gloveOverHair"/><string name="_inlink" value="shoot2/1/rGlove"/></canvas></imgdir><imgdir name="3"><uol name="lGlove" value="../0/lGlove"/><uol name="rGlove" value="../0/rGlove"/></imgdir><imgdir name="4"><canvas name="lGlove" width="1" height="1"><vector name="origin" x="16" y="10"/><imgdir name="map"><vector name="navel" x="0" y="0"/></imgdir><string name="z" value="gloveOverBody"/><string name="_inlink" value="shoot2/0/lGlove"/></canvas><canvas name="rGlove" width="1" height="1"><vector name="origin" x="0" y="10"/><imgdir name="map"><vector name="navel" x="0" y="0"/></imgdir><string name="z" value="gloveOverHair"/><string name="_inlink" value="shoot2/0/rGlove"/></canvas></imgdir></imgdir><imgdir name="shootF"><imgdir name="0"><canvas name="lGlove" width="12" height="11"><vector name="origin" x="29" y="17"/><imgdir name="map"><vector name="navel" x="0" y="0"/></imgdir><string name="z" value="gloveOverBody"/><string name="_hash" value="bef27f3dbc10ceee4ad2124565d0eae04fa5be05e152b830e34a1f2ee7dd75d3"/></canvas><canvas name="rGlove" width="12" height="10"><vector name="origin" x="13" y="18"/><imgdir name="map"><vector name="navel" x="0" y="0"/></imgdir><string name="z" value="gloveOverHair"/><string name="_hash" value="d1f44d285d84a1f69ed50e90c051bb2c64333c43b5164b72091d9d94aa6abd11"/></canvas></imgdir><imgdir name="1"><canvas name="lGlove" width="12" height="11"><vector name="origin" x="31" y="17"/><imgdir name="map"><vector name="navel" x="0" y="0"/></imgdir><string name="z" value="gloveOverBody"/><string name="_hash" value="2db893f24202afa51c52fd26e9aa6eaf90fe18a4feb288d345516488ccbe402b"/></canvas><canvas name="rGlove" width="11" height="12"><vector name="origin" x="-1" y="15"/><imgdir name="map"><vector name="navel" x="0" y="0"/></imgdir><string name="z" value="gloveBelowMailArm"/><string name="_hash" value="55d628f838bd66780b3a2450857350cfe9c8c025517694b4758aa237eca970da"/></canvas></imgdir><imgdir name="2"><uol name="lGlove" value="../1/lGlove"/><uol name="rGlove" value="../1/rGlove"/></imgdir></imgdir><imgdir name="proneStab"><imgdir name="0"><canvas name="lGlove" width="11" height="9"><vector name="origin" x="40" y="6"/><imgdir name="map"><vector name="navel" x="0" y="0"/></imgdir><string name="z" value="gloveOverBody"/><string name="_hash" value="8262d32c0aed4537b2744e35bde1ccc424025f8e03fe0aa45bcaf8176c837b3f"/></canvas><canvas name="rGlove" width="13" height="10"><vector name="origin" x="14" y="7"/><imgdir name="map"><vector name="navel" x="4" y="-3"/></imgdir><string name="z" value="gloveOverHair"/><string name="_hash" value="adceeab21e7e185a2460875fcf1237324d23eaa8c0d2cc3c54fff96b3fc3f2a8"/></canvas></imgdir><imgdir name="1"><uol name="lGlove" value="../0/lGlove"/><canvas name="rGlove" width="12" height="9"><vector name="origin" x="29" y="6"/><imgdir name="map"><vector name="navel" x="0" y="0"/></imgdir><string name="z" value="gloveOverHair"/><string name="_hash" value="a6a33d95337d254c9af46e742ff1f9e9e01f25c4789817b05c75fe1ed39dcb78"/></canvas></imgdir></imgdir><imgdir name="prone"><imgdir name="0"><uol name="lGlove" value="../../proneStab/0/lGlove"/><uol name="rGlove" value="../../proneStab/0/rGlove"/></imgdir></imgdir><imgdir name="heal"><imgdir name="0"><uol name="lGlove" value="../../alert/1/lGlove"/><uol name="rGlove" value="../../alert/1/rGlove"/></imgdir><imgdir name="1"><uol name="lGlove" value="../../swingO2/1/lGlove"/><uol name="rGlove" value="../../swingO2/1/rGlove"/></imgdir><imgdir name="2"><uol name="lGlove" value="../../swingO2/0/lGlove"/><uol name="rGlove" value="../../swingO2/0/rGlove"/></imgdir></imgdir><imgdir name="fly"><imgdir name="0"><canvas name="lGlove" width="1" height="1"><vector name="origin" x="12" y="8"/><imgdir name="map"><vector name="navel" x="0" y="0"/></imgdir><string name="z" value="gloveOverHair"/><string name="_inlink" value="stand2/0/lGlove"/></canvas><canvas name="rGlove" width="10" height="10"><vector name="origin" x="1" y="13"/><imgdir name="map"><vector name="navel" x="0" y="0"/></imgdir><string name="z" value="gloveOverHair"/><string name="_hash" value="a553c12ed429b9a3a314f308d43a6e4332a5cf4b8e3d71be70d83d76feab9a19"/></canvas></imgdir><imgdir name="1"><uol name="lGlove" value="../0/lGlove"/><uol name="rGlove" value="../0/rGlove"/></imgdir></imgdir><imgdir name="jump"><imgdir name="0"><canvas name="lGlove" width="1" height="1"><vector name="origin" x="11" y="7"/><imgdir name="map"><vector name="navel" x="0" y="0"/></imgdir><string name="z" value="gloveOverHair"/><string name="_inlink" value="stand2/0/lGlove"/></canvas><canvas name="rGlove" width="10" height="10"><vector name="origin" x="0" y="12"/><imgdir name="map"><vector name="navel" x="0" y="0"/></imgdir><string name="z" value="gloveOverHair"/><string name="_hash" value="966fd5d270018a60ca26ec4703113b91cd6f5c3f9170ca35bfda388080872eac"/></canvas></imgdir></imgdir><imgdir name="sit"><imgdir name="0"><canvas name="lGlove" width="7" height="5"><vector name="origin" x="9" y="2"/><imgdir name="map"><vector name="navel" x="0" y="0"/></imgdir><string name="z" value="gloveOverBody"/></canvas><canvas name="rGlove" width="10" height="9"><vector name="origin" x="1" y="3"/><imgdir name="map"><vector name="navel" x="0" y="0"/></imgdir><string name="z" value="glove"/><string name="_hash" value="452ce8d22c5f5c9d4957dfc174d524c5e412cfedff212a6516caba78ad47c46c"/></canvas></imgdir></imgdir><imgdir name="ladder"><imgdir name="0"><canvas name="rGlove" width="22" height="19"><vector name="origin" x="10" y="22"/><imgdir name="map"><vector name="navel" x="0" y="0"/></imgdir><string name="z" value="backGlove"/><string name="_hash" value="e9be17e5aa1f0e555b5965f102572a715562bb181c2769fd1860928ce8a7dac8"/></canvas></imgdir><imgdir name="1"><canvas name="rGlove" width="22" height="19"><vector name="origin" x="12" y="22"/><imgdir name="map"><vector name="navel" x="0" y="0"/></imgdir><string name="z" value="backGlove"/><string name="_hash" value="bc28f4071af527ce6596339ae784987ed61316f79319a9bb645a9a0ce3b46137"/></canvas></imgdir></imgdir><imgdir name="rope"><imgdir name="0"><canvas name="rGlove" width="16" height="9"><vector name="origin" x="8" y="19"/><imgdir name="map"><vector name="navel" x="0" y="0"/></imgdir><string name="z" value="backGlove"/><string name="_hash" value="dd075956395f1d96f81b5258c268b47b530d026909f456eaf8e8f7f778a94b58"/></canvas></imgdir><imgdir name="1"><canvas name="rGlove" width="9" height="5"><vector name="origin" x="4" y="12"/><imgdir name="map"><vector name="navel" x="0" y="0"/></imgdir><string name="z" value="backGlove"/><string name="_hash" value="f8c0181fccdd1f060866008fed379516fcdf4c952b92dbc261fda84c64558918"/></canvas></imgdir></imgdir></imgdir>