<?xml version="1.0" encoding="UTF-8" standalone="yes"?><imgdir name="9330078.img"><imgdir name="info"><imgdir name="speak"><string name="0" value="n0"/><string name="1" value="n1"/></imgdir><imgdir name="script"><imgdir name="0"><string name="script" value="CandleEvent"/></imgdir></imgdir></imgdir><imgdir name="stand"><canvas name="0" width="99" height="119"><vector name="origin" x="47" y="119"/><int name="z" value="0"/><string name="_hash" value="d79d946d973e970a5e9ba0a4d5a64d4f0bd02213846c2b0982ec2eb4deab56d3"/></canvas><canvas name="1" width="97" height="120"><vector name="origin" x="47" y="120"/><int name="z" value="0"/><string name="_hash" value="f34aa7d13328e1811cbbf8d8fff92a7f1c8888b2364d3c9a963cbfa1a308e595"/></canvas><canvas name="2" width="97" height="118"><vector name="origin" x="47" y="118"/><int name="z" value="0"/><string name="_hash" value="b70d4bf51a2a433a453df4e2e33803d917fba1e4ff4e0f4e92f0499659fb25fd"/></canvas><canvas name="3" width="100" height="119"><vector name="origin" x="48" y="119"/><int name="z" value="0"/><string name="_hash" value="5b00ea05521e3d3d6c440483fc22744e45c14e8ad10008ebfb5309924f44a13f"/></canvas><canvas name="4" width="97" height="120"><vector name="origin" x="47" y="120"/><int name="z" value="0"/><string name="_hash" value="38ff9561b18ee0b65241efffac677eb377f23369e07e5b423f2754ce2c74bfdc"/></canvas><canvas name="5" width="98" height="118"><vector name="origin" x="48" y="118"/><int name="z" value="0"/><string name="_hash" value="aa18db018318376fc05c2427c4e6046f72dd73109103fb03f0e44659afb20fb4"/></canvas><canvas name="6" width="99" height="119"><vector name="origin" x="47" y="119"/><int name="z" value="0"/><string name="_hash" value="d9d0aee03e4dee11cbbcc1b32e0dfc65ca3aba771758eae9f7dfe041ec22c40b"/></canvas><canvas name="7" width="98" height="120"><vector name="origin" x="48" y="120"/><int name="z" value="0"/><string name="_hash" value="e5cb0ede098f5d16c4c2bb751173d040454bbc770a3d239af7f3e05a1b9f7bd8"/></canvas><canvas name="8" width="97" height="115"><vector name="origin" x="47" y="115"/><int name="z" value="0"/><string name="_hash" value="3b14ffe01e5357f9f1d64666074ea6293945072669297829a628c0ad6963ec45"/></canvas><canvas name="9" width="99" height="119"><vector name="origin" x="47" y="119"/><int name="z" value="0"/><string name="_hash" value="da56eef6243017e5c4b382e16020a03ec4aae243b9a6fee89299d2581266966b"/></canvas><canvas name="10" width="97" height="120"><vector name="origin" x="47" y="120"/><int name="z" value="0"/><string name="_hash" value="aaed65d34f730b4002b411025a88293a790f15a5b6dd4b4641301a6598722fc2"/></canvas><canvas name="11" width="97" height="118"><vector name="origin" x="47" y="118"/><int name="z" value="0"/><string name="_hash" value="6c2e4a548f18953d153ecf2a78fc4876b77ef3febf3304ab910e9230153793c6"/></canvas><canvas name="12" width="99" height="119"><vector name="origin" x="47" y="119"/><int name="z" value="0"/><string name="_hash" value="d435490ee5d73252f1dedacf3fc6534646bfa3f9d6207641d0058d3f38dde303"/></canvas><canvas name="13" width="99" height="119"><vector name="origin" x="47" y="119"/><int name="z" value="0"/><string name="_hash" value="e9c068608524679e2483655521e210e316cbb29b2a04bde292938931bc4549e5"/></canvas><canvas name="14" width="99" height="119"><vector name="origin" x="47" y="119"/><int name="z" value="0"/><string name="_hash" value="7c289e2357d860f150a85eeb651f3a2d2736effa35555eef611051209baf79fd"/></canvas><canvas name="15" width="97" height="120"><vector name="origin" x="47" y="120"/><int name="z" value="0"/><string name="_hash" value="66cda6de9939d60095e43366a8bdb46ace31ff3cf05d340a60b3272ce7ece19e"/></canvas><canvas name="16" width="97" height="118"><vector name="origin" x="47" y="118"/><int name="z" value="0"/><string name="_hash" value="71acdcaab101c39606d9ecb73594efdfca618ce4133b63c66263fa70cab4ed54"/></canvas></imgdir><imgdir name="eye"><canvas name="0" width="99" height="119"><vector name="origin" x="47" y="119"/><int name="delay" value="90"/><string name="_hash" value="604359176c10602689a23a82c9f1da094b80a2fedf5eeb212e9df800be9e1a61"/></canvas><canvas name="1" width="98" height="120"><vector name="origin" x="47" y="120"/><int name="delay" value="90"/><string name="_hash" value="3ba40d335cb845bb7e93aac22317d97d972450f293f6096038d76759d2330a55"/></canvas><canvas name="2" width="97" height="118"><vector name="origin" x="47" y="118"/><int name="delay" value="90"/><string name="_hash" value="195708e5a438f92dc9b4a512049aa1d6425d9ec104e0bf655240e2fd770b49bc"/></canvas><canvas name="3" width="97" height="118"><vector name="origin" x="47" y="118"/><int name="delay" value="90"/><string name="_hash" value="2daa158c36c825689e6393cfc68be68d5727fbbd62c3cb2cf9448dda29a9d91d"/></canvas><canvas name="4" width="1" height="1"><vector name="origin" x="47" y="118"/><int name="delay" value="90"/><string name="_inlink" value="eye/2"/></canvas></imgdir><imgdir name="say"><canvas name="0" width="99" height="119"><vector name="origin" x="47" y="119"/><int name="z" value="0"/><string name="_hash" value="89f1cb7395a4aba520f037d0532995df725b7ecf7d23b8d5925fb691224a5d9e"/></canvas><canvas name="1" width="97" height="120"><vector name="origin" x="47" y="120"/><int name="z" value="0"/><string name="_hash" value="8b02e777d6868d2c4ab1d72b117c775017bd113ce949eca40d0dbc4384ae2560"/></canvas><canvas name="2" width="97" height="118"><vector name="origin" x="47" y="118"/><int name="z" value="0"/><string name="_hash" value="09fbdce7cd0e5372c6a8684c2687e5b1ebdb84afe774d9f469a3259deb41b8dd"/></canvas><canvas name="3" width="97" height="118"><vector name="origin" x="47" y="118"/><int name="z" value="0"/><string name="_hash" value="573e33e4be09ac2c9e105f5fecc6ea07a12b77cfa99d3d04e1fb85c1945bd3dd"/></canvas><canvas name="4" width="1" height="1"><vector name="origin" x="47" y="118"/><int name="z" value="0"/><string name="_inlink" value="say/2"/></canvas></imgdir></imgdir>