<?xml version="1.0" encoding="UTF-8" standalone="yes"?><imgdir name="9600044.img"><imgdir name="info"><int name="bodyAttack" value="1"/><int name="level" value="30"/><int name="maxHP" value="750"/><int name="maxMP" value="0"/><int name="speed" value="1"/><int name="PADamage" value="100"/><int name="PDDamage" value="40"/><int name="MADamage" value="100"/><int name="MDDamage" value="40"/><int name="acc" value="57"/><int name="eva" value="20"/><int name="exp" value="53"/><int name="undead" value="0"/><int name="pushed" value="0"/><float name="fs" value="10.0"/><int name="summonType" value="1"/></imgdir><imgdir name="move"><canvas name="0" width="70" height="76"><vector name="origin" x="23" y="75"/><vector name="lt" x="-35" y="-76"/><vector name="rb" x="35" y="0"/><vector name="head" x="0" y="-76"/><int name="delay" value="120"/><string name="_hash" value="52c230de6d6c9155f86c3018c68af90a59af339cd3b601cb26c9d4920fe88e47"/></canvas><canvas name="1" width="63" height="80"><vector name="origin" x="15" y="79"/><vector name="lt" x="-35" y="-80"/><vector name="rb" x="35" y="0"/><vector name="head" x="0" y="-80"/><int name="delay" value="120"/><string name="_hash" value="939823aecea77d240129647031ec056f0f985481a9c98107d649397802393fe2"/></canvas><canvas name="2" width="59" height="79"><vector name="origin" x="12" y="78"/><vector name="lt" x="-29" y="-79"/><vector name="rb" x="30" y="0"/><vector name="head" x="0" y="-79"/><int name="delay" value="120"/><string name="_hash" value="d1eebc87193e7d401acbfa7261fe2f9ef181d8fcfff362014f10631934fd347f"/></canvas><canvas name="3" width="67" height="75"><vector name="origin" x="19" y="74"/><vector name="lt" x="-33" y="-75"/><vector name="rb" x="34" y="0"/><vector name="head" x="0" y="-75"/><int name="delay" value="120"/><string name="_hash" value="95be9386e9cc702e3f2534f0c7172f5ad424e3cc2cf3b77d5219c864721d520e"/></canvas><canvas name="4" width="66" height="74"><vector name="origin" x="19" y="73"/><vector name="lt" x="-39" y="-74"/><vector name="rb" x="27" y="0"/><vector name="head" x="-6" y="-74"/><int name="delay" value="120"/><string name="_hash" value="083c64d99c221f6fb4386a742625c7286805ea2d12a6eb363c514eafe805f4a0"/></canvas><canvas name="5" width="72" height="76"><vector name="origin" x="24" y="75"/><vector name="lt" x="-44" y="-74"/><vector name="rb" x="28" y="2"/><vector name="head" x="-8" y="-74"/><int name="delay" value="120"/><string name="_hash" value="de87c5acfbc7c900daf085b0cfc934fe86548bc5c4f3421bc727c8f970150026"/></canvas></imgdir><imgdir name="stand"><canvas name="0" width="70" height="76"><vector name="origin" x="23" y="75"/><int name="delay" value="120"/><vector name="lt" x="-35" y="-76"/><vector name="rb" x="35" y="0"/><vector name="head" x="0" y="-76"/><string name="_hash" value="ff6a232768b21e150e5fd9a47c0ac327e065ccec9373a3f48fb6e99f470c0145"/></canvas><canvas name="1" width="71" height="78"><vector name="origin" x="23" y="77"/><int name="delay" value="120"/><vector name="lt" x="-35" y="-78"/><vector name="rb" x="36" y="0"/><vector name="head" x="0" y="-78"/><string name="_hash" value="0a8cad1837298e3c3aafcbdff0308e79d0c0ea91f8efdc32b0bcd02b04a25c22"/></canvas><canvas name="2" width="69" height="72"><vector name="origin" x="22" y="71"/><int name="delay" value="120"/><vector name="lt" x="-34" y="-72"/><vector name="rb" x="35" y="0"/><vector name="head" x="0" y="-72"/><string name="_hash" value="7b902006f1b281518506a139b4f3176a8f839acf41412a63a46171f226e1ec3b"/></canvas><canvas name="3" width="69" height="75"><vector name="origin" x="21" y="74"/><int name="delay" value="120"/><vector name="lt" x="-34" y="-75"/><vector name="rb" x="35" y="0"/><vector name="head" x="0" y="-75"/><string name="_hash" value="506f38d7228b76d4032d668b9ff7bb96564a652c11d87913ba28cb63357e20d9"/></canvas><canvas name="4" width="69" height="78"><vector name="origin" x="20" y="77"/><int name="delay" value="120"/><vector name="lt" x="-34" y="-78"/><vector name="rb" x="35" y="0"/><vector name="head" x="0" y="-78"/><string name="_hash" value="d8b5fa1fc6680a11b0ae0d5faeec938dc66d81abeb508833180b8f6edbaaaae1"/></canvas><canvas name="5" width="1" height="1"><vector name="origin" x="21" y="74"/><int name="delay" value="120"/><vector name="lt" x="-34" y="-75"/><vector name="rb" x="35" y="0"/><vector name="head" x="0" y="-75"/><string name="_inlink" value="stand/3"/></canvas></imgdir><imgdir name="hit1"><canvas name="0" width="70" height="76"><vector name="origin" x="35" y="76"/><int name="delay" value="200"/><vector name="lt" x="-35" y="-76"/><vector name="rb" x="35" y="0"/><vector name="head" x="0" y="-76"/><string name="_hash" value="a83b17c26e04089a5a99398997e1e34ce3d8c85221b01c2f231a643cc23119b4"/></canvas><canvas name="1" width="82" height="88"><vector name="origin" x="35" y="91"/><int name="delay" value="200"/><vector name="lt" x="-35" y="-91"/><vector name="rb" x="47" y="-4"/><vector name="head" x="6" y="-91"/><string name="_hash" value="bfd88c0c7cc2c1fa9d25a9495289d3e7ab4cd8ab66b316449de9fb21cb9616e8"/></canvas></imgdir><imgdir name="die1"><canvas name="0" width="1" height="1"><vector name="origin" x="23" y="75"/><vector name="head" x="-1" y="-76"/><int name="delay" value="150"/><string name="_inlink" value="hit1/0"/></canvas><canvas name="1" width="1" height="1"><vector name="origin" x="20" y="91"/><vector name="head" x="0" y="-88"/><int name="delay" value="150"/><string name="_inlink" value="hit1/1"/></canvas><canvas name="2" width="94" height="91"><vector name="origin" x="16" y="100"/><vector name="head" x="16" y="-103"/><int name="delay" value="150"/><string name="_hash" value="555385c166db46e6a6c11d2c247b61524782600880f515c2f89fc82b3af11e77"/></canvas><canvas name="3" width="98" height="59"><vector name="origin" x="0" y="71"/><vector name="head" x="15" y="-67"/><int name="delay" value="150"/><string name="_hash" value="489777584c7e6d52f6d3d5f26657445a5a08a4bd99ec883d7f1c12071d1f9aac"/></canvas><canvas name="4" width="114" height="72"><vector name="origin" x="3" y="70"/><vector name="head" x="16" y="-73"/><int name="delay" value="150"/><string name="_hash" value="181142505c774958bfd62ca47b2b57414561fe77fce0f57d0e6533d92baacf9a"/></canvas><canvas name="5" width="121" height="67"><vector name="origin" x="4" y="72"/><vector name="head" x="16" y="-73"/><int name="delay" value="150"/><string name="_hash" value="2582a1af09ee06a747ae9ad3e934185fe1fd84b37a9a8f87d8dafa6a245a3147"/></canvas><canvas name="6" width="134" height="75"><vector name="origin" x="8" y="74"/><vector name="head" x="45" y="-67"/><int name="delay" value="150"/><int name="a0" value="255"/><int name="a1" value="0"/><string name="_hash" value="2c02dfc507082e5e20f0f22a01a7035b188c9ecd7a74724b262fcfbc03885a71"/></canvas><canvas name="7" width="125" height="73"><vector name="origin" x="-1" y="72"/><vector name="head" x="16" y="-75"/><int name="delay" value="150"/><string name="_hash" value="04d6b8adfbd69c19078a928312e48f41cb2f10b526d353a000d949cca908d902"/></canvas><canvas name="8" width="114" height="90"><vector name="origin" x="-12" y="89"/><vector name="head" x="39" y="-90"/><int name="delay" value="150"/><string name="_hash" value="dafe854a11266806784a49f57854ee3ff683b3a55c5c1b4a83e3c6d6390dc069"/></canvas><canvas name="9" width="101" height="112"><vector name="origin" x="-25" y="111"/><vector name="head" x="61" y="-112"/><int name="delay" value="150"/><string name="_hash" value="726b7c30ea966073328440817e2e2d2f91af0ef68008036a79e75cb8f9f9bcb9"/></canvas><canvas name="10" width="80" height="135"><vector name="origin" x="-46" y="134"/><vector name="head" x="88" y="-135"/><int name="delay" value="150"/><string name="_hash" value="87587ec93a63100de06003d33aafb1e060e4ba37280cac6e593f92b6fbc58924"/></canvas><canvas name="11" width="58" height="137"><vector name="origin" x="-68" y="136"/><vector name="head" x="95" y="-137"/><int name="delay" value="150"/><string name="_hash" value="1ea13f0722d27889fba1d4c1c336b206baff72f6ad3ad2a2961aaeff0733335c"/></canvas><canvas name="12" width="44" height="137"><vector name="origin" x="-84" y="136"/><vector name="head" x="103" y="-137"/><int name="delay" value="150"/><string name="_hash" value="0c348fd88ac9654401a55aab4d012cc6939a61d44fc5dfed44f26c3a872664c7"/></canvas></imgdir></imgdir>