<?xml version="1.0" encoding="UTF-8" standalone="yes"?><imgdir name="SpeedAnimationQuiz.img"><imgdir name="BeijingOlympic"><imgdir name="AniQuiz"><imgdir name="0"><imgdir name="info"><string name="answer" value="击剑"/></imgdir><imgdir name="ani"><canvas name="0" width="122" height="99"><vector name="origin" x="-81" y="-163"/><int name="delay" value="120"/><string name="_hash" value="6b5cab6c8aa607da637157bb20fd9958146f909033f5b478aae9288ccfd5a644"/></canvas><canvas name="1" width="121" height="99"><vector name="origin" x="-81" y="-162"/><int name="delay" value="120"/><string name="_hash" value="42acf4e1abf9a1620e6acf7c347ae4c5cab7f0df5049ac72c9efbde4b0419858"/></canvas><canvas name="2" width="123" height="100"><vector name="origin" x="-81" y="-160"/><int name="delay" value="120"/><string name="_hash" value="71f0e322ca4a308529d390645154bc045de77b510b8a6afb068d6c6732ec9fe1"/></canvas><canvas name="3" width="124" height="100"><vector name="origin" x="-81" y="-159"/><int name="delay" value="120"/><string name="_hash" value="a5116b96f6746a42f46d31130a4dffee96c10e09e5c932ec3573a6945d81bc7d"/></canvas><canvas name="4" width="124" height="99"><vector name="origin" x="-81" y="-161"/><int name="delay" value="120"/><string name="_hash" value="53aa8391d46dbf4aeb6bcb4d72762404264b51745725a2381fe3f16cda432a9b"/></canvas><canvas name="5" width="123" height="99"><vector name="origin" x="-81" y="-162"/><int name="delay" value="120"/><string name="_hash" value="2866d301e65aa31bbab204643045c7526e8a17f29fb39d352b352aaa61f3e6ff"/></canvas><canvas name="6" width="1" height="1"><vector name="origin" x="-81" y="-163"/><int name="delay" value="120"/><string name="_inlink" value="BeijingOlympic/AniQuiz/0/ani/0"/></canvas><canvas name="7" width="1" height="1"><vector name="origin" x="-81" y="-162"/><int name="delay" value="120"/><string name="_inlink" value="BeijingOlympic/AniQuiz/0/ani/1"/></canvas><canvas name="8" width="1" height="1"><vector name="origin" x="-81" y="-160"/><int name="delay" value="120"/><string name="_inlink" value="BeijingOlympic/AniQuiz/0/ani/2"/></canvas><canvas name="9" width="1" height="1"><vector name="origin" x="-81" y="-159"/><int name="delay" value="120"/><string name="_inlink" value="BeijingOlympic/AniQuiz/0/ani/3"/></canvas><canvas name="10" width="1" height="1"><vector name="origin" x="-81" y="-161"/><int name="delay" value="120"/><string name="_inlink" value="BeijingOlympic/AniQuiz/0/ani/4"/></canvas><canvas name="11" width="1" height="1"><vector name="origin" x="-81" y="-162"/><int name="delay" value="120"/><string name="_inlink" value="BeijingOlympic/AniQuiz/0/ani/5"/></canvas><canvas name="12" width="1" height="1"><vector name="origin" x="-81" y="-163"/><int name="delay" value="120"/><string name="_inlink" value="BeijingOlympic/AniQuiz/0/ani/0"/></canvas><canvas name="13" width="152" height="96"><vector name="origin" x="-52" y="-164"/><int name="delay" value="120"/><string name="_hash" value="dd9633c017307fd99624737d4fd25303a35a8ead57d8fbee40fff856a472d5e8"/></canvas><canvas name="14" width="143" height="96"><vector name="origin" x="-60" y="-164"/><int name="delay" value="120"/><string name="_hash" value="503e30486df174a0532ef2d70d3b14d202861f56239dc11379b8a85500103225"/></canvas><canvas name="15" width="141" height="96"><vector name="origin" x="-62" y="-165"/><int name="delay" value="120"/><string name="_hash" value="0ed215a4c64bce11502a6565fec0433fc7fdfb58dfc2d4bdd104e6caa8609d12"/></canvas><canvas name="16" width="183" height="96"><vector name="origin" x="-36" y="-165"/><int name="delay" value="120"/><string name="_hash" value="6a5f75587c72b587cf25dea8bc4fea8a2628877b6bfd0d0606a559e1853571a4"/></canvas><canvas name="17" width="189" height="96"><vector name="origin" x="-35" y="-165"/><int name="delay" value="120"/><string name="_hash" value="f4efaedac01ff055f5d033b36e213401720f4319dbb06f2c835f6db0950bbabc"/></canvas><canvas name="18" width="189" height="96"><vector name="origin" x="-35" y="-165"/><int name="delay" value="120"/><string name="_hash" value="cbc8ccad25f43d6b674af24a9b2481d4dbed8c218ee41e313b45262f9bb7a6b5"/></canvas><canvas name="19" width="152" height="96"><vector name="origin" x="-48" y="-165"/><int name="delay" value="120"/><string name="_hash" value="a3bc74cdc9d49e99aa75425cf5b1a7c24f6b48e3675106c95d2b561c290d659f"/></canvas><canvas name="20" width="145" height="96"><vector name="origin" x="-56" y="-165"/><int name="delay" value="120"/><string name="_hash" value="bac91707da864353180c52214f10121abd32e48a3479e2cc698b106993485d8e"/></canvas><canvas name="21" width="141" height="96"><vector name="origin" x="-62" y="-165"/><int name="delay" value="120"/><string name="_hash" value="4bf20f4a29a705b41b5de62228bbfb5afbef76d4c78a7d06dbff7ce06c48ca63"/></canvas></imgdir></imgdir><imgdir name="1"><imgdir name="info"><string name="answer" value="马术"/></imgdir><imgdir name="ani"><canvas name="0" width="95" height="125"><vector name="origin" x="-86" y="-132"/><int name="delay" value="150"/><string name="_hash" value="af95a37f1afc34c9dcf18bb66f485f864ed0a6028ba5c59ed6bec52a4099664e"/></canvas><canvas name="1" width="96" height="123"><vector name="origin" x="-85" y="-134"/><int name="delay" value="150"/><string name="_hash" value="089877c723fb31435773ea28ba090986efb7e30cfb311fba39cba8df2ed1b066"/></canvas><canvas name="2" width="97" height="121"><vector name="origin" x="-83" y="-136"/><int name="delay" value="150"/><string name="_hash" value="7a9fdffa9499e1e4629f19649dfa28de2b407a81ba5d07cfa1ce5c2026a64080"/></canvas><canvas name="3" width="96" height="123"><vector name="origin" x="-85" y="-134"/><int name="delay" value="150"/><string name="_hash" value="fc558701798326020c0f59cf47efd9dd2a5bef878c493dcab6b39d83dfee6c92"/></canvas><canvas name="4" width="141" height="125"><vector name="origin" x="-40" y="-132"/><int name="delay" value="150"/><string name="_hash" value="68b72883f736410702848c6b13ec75edc6b17545587ef95ab96db3846bb34e94"/></canvas><canvas name="5" width="121" height="123"><vector name="origin" x="-60" y="-134"/><int name="delay" value="150"/><string name="_hash" value="4272f86602953a65a1ebccb6f29b4dd5f6001bdbaa190d155e68464f69e4593e"/></canvas><canvas name="6" width="100" height="121"><vector name="origin" x="-80" y="-136"/><int name="delay" value="150"/><string name="_hash" value="92275d70ff6a954c44c1861cd1dfe817656624b174d6393ab2404d337a5206a9"/></canvas><canvas name="7" width="96" height="123"><vector name="origin" x="-85" y="-134"/><int name="delay" value="150"/><string name="_hash" value="4eb627136a8ac16dccdbf83383d9f9e4bab75b9b6906130c84759062b6b60bba"/></canvas><canvas name="8" width="102" height="145"><vector name="origin" x="-86" y="-112"/><int name="delay" value="150"/><string name="_hash" value="9ee89f3998b26cf84dfacea21aa03ea8a2efa7ec7fa6a2cc916fbe334828ef84"/></canvas><canvas name="9" width="117" height="141"><vector name="origin" x="-85" y="-116"/><int name="delay" value="150"/><string name="_hash" value="b5c944117223e404f78a0bcdcc6ba962d554f214544fc5c5f6eed5f07cde42f2"/></canvas><canvas name="10" width="128" height="122"><vector name="origin" x="-83" y="-137"/><int name="delay" value="150"/><string name="_hash" value="e43f31eb7ab85a6f1bc20f9d8478b754f1a40d05be93f1f3147ed8802f6fbd8d"/></canvas><canvas name="11" width="146" height="126"><vector name="origin" x="-85" y="-132"/><int name="delay" value="150"/><string name="_hash" value="06d54446c0b6e54144ac0a2c1ed1a3ab93332897aa1e7cf0e4edbdbc1fde6daf"/></canvas></imgdir></imgdir><imgdir name="2"><imgdir name="info"><string name="answer" value="跳水"/></imgdir><imgdir name="ani"><canvas name="0" width="62" height="69"><vector name="origin" x="-115" y="-196"/><int name="delay" value="170"/><string name="_hash" value="600027c493a066bfaf9dc0aec7e667ceed45228af0e2813e3efb2742d09b2464"/></canvas><canvas name="1" width="62" height="69"><vector name="origin" x="-113" y="-196"/><int name="delay" value="170"/><string name="_hash" value="8b119c86ce59cac15989cf93b0751148ab190f4b719a5dc90823e5e35905df1d"/></canvas><canvas name="2" width="65" height="70"><vector name="origin" x="-113" y="-201"/><int name="delay" value="170"/><string name="_hash" value="8093f7f9b6024abbd3f89e91e9ddaf948709b4cd7fedab9c953f46c9a43014db"/></canvas><uol name="3" value="0"/><uol name="4" value="1"/><uol name="5" value="2"/><uol name="6" value="0"/><uol name="7" value="1"/><uol name="8" value="2"/><canvas name="9" width="56" height="87"><vector name="origin" x="-119" y="-146"/><int name="delay" value="170"/><string name="_hash" value="c1aecd01ee5b363f9952d9c960dac3c2367a753f337ff5c1ab321b18d93d1504"/></canvas><canvas name="10" width="58" height="83"><vector name="origin" x="-114" y="-123"/><int name="delay" value="170"/><string name="_hash" value="82721ee6c9c3f7f4b59350e0cf4667eb62be89aa6366fb33b23f9ca6baf98859"/></canvas><canvas name="11" width="58" height="84"><vector name="origin" x="-112" y="-150"/><int name="delay" value="170"/><string name="_hash" value="9e74d20179b6c5726c987f9d2db8f29c73fd2ad81dc6047ad42f029f28471522"/></canvas><canvas name="12" width="86" height="48"><vector name="origin" x="-103" y="-228"/><int name="delay" value="170"/><string name="_hash" value="c945dd9ff72e81b50833419941573087cdb65e2c23d45cc25953ed128572abcd"/></canvas><canvas name="13" width="89" height="21"><vector name="origin" x="-101" y="-256"/><int name="delay" value="170"/><string name="_hash" value="76ed1191b44ddb8ce1fc0178b6eefcc42e945cf7ca9ca5a5dd7166dd6e2b0da6"/></canvas></imgdir></imgdir><imgdir name="3"><imgdir name="info"><string name="answer" value="游泳"/></imgdir><imgdir name="ani"><canvas name="0" width="122" height="106"><vector name="origin" x="-82" y="-158"/><int name="delay" value="200"/><string name="_hash" value="c3b98e8d98a08b73e565a87e15d3122bee8414d29a3038388d6d4dcdecf64cb9"/></canvas><canvas name="1" width="120" height="106"><vector name="origin" x="-82" y="-158"/><int name="delay" value="200"/><string name="_hash" value="0bb554676f044dbe4fd27e7fa046ffb0ebe46c27d72f016c1d1785326ec6d21f"/></canvas><canvas name="2" width="122" height="106"><vector name="origin" x="-82" y="-158"/><int name="delay" value="200"/><string name="_hash" value="938a1ccfeafb516bfb72e47cf8d7caca7e8e57b68fd487ad31299cf9c2649ed4"/></canvas><canvas name="3" width="122" height="106"><vector name="origin" x="-82" y="-158"/><int name="delay" value="200"/><string name="_hash" value="25f97585d69f5d764278890a54e7f3d498e58caae6c3333b72e790036cbd8681"/></canvas><canvas name="4" width="120" height="106"><vector name="origin" x="-82" y="-158"/><int name="delay" value="200"/><string name="_hash" value="9a19e72ae298092bd266ede5479da3d1e125d1fc46270b92128ba9e4155d913b"/></canvas><canvas name="5" width="122" height="106"><vector name="origin" x="-82" y="-158"/><int name="delay" value="200"/><string name="_hash" value="72772fededa514e625cdbdba7ae3e4f02310b8de0fa2729a14fb557ab9427041"/></canvas></imgdir></imgdir><imgdir name="4"><imgdir name="info"><string name="answer" value="田径"/></imgdir><imgdir name="ani"><canvas name="0" width="69" height="73"><vector name="origin" x="-106" y="-185"/><int name="delay" value="130"/><string name="_hash" value="5178e7bbe0695066dd665e6f7d9b19734f20f6a47fffbb338819abe686bd44fd"/></canvas><canvas name="1" width="63" height="81"><vector name="origin" x="-106" y="-177"/><int name="delay" value="130"/><string name="_hash" value="641cdf3f2aa25b697bce466d8ca4b0d1092b957b4d554dcd2951df1f134448ab"/></canvas><canvas name="2" width="69" height="88"><vector name="origin" x="-106" y="-170"/><int name="delay" value="130"/><string name="_hash" value="f0597c9286ef09f4a51502dfd890ff7170c3f517a989047c4315d8873655e761"/></canvas><canvas name="3" width="63" height="90"><vector name="origin" x="-106" y="-168"/><int name="delay" value="130"/><string name="_hash" value="8465dc76e78a7ce629d79d8d178f47b7dbe95ca696e5c94ff8c4535c694b2f69"/></canvas><canvas name="4" width="69" height="93"><vector name="origin" x="-106" y="-165"/><int name="delay" value="130"/><string name="_hash" value="75fb5b987d555a3f923a7e0aa62eeecf0a3d4cdd180892e81a9ab5929efde5da"/></canvas><canvas name="5" width="68" height="95"><vector name="origin" x="-106" y="-163"/><int name="delay" value="130"/><string name="_hash" value="1aace98210a8a1e6135bd914257679f0b2239cf471332379d401c92eb9c013c9"/></canvas><canvas name="6" width="67" height="72"><vector name="origin" x="-108" y="-186"/><int name="delay" value="130"/><string name="_hash" value="80fe38fb30c339de8db8a13a71f9f95c2a306e470ac24530e87b64814de4b14a"/></canvas><canvas name="7" width="66" height="71"><vector name="origin" x="-104" y="-187"/><int name="delay" value="130"/><string name="_hash" value="40e1ed8f1554239179ff238d2bab18d79320e671a936877d3557619bee2ed9ad"/></canvas><canvas name="8" width="67" height="72"><vector name="origin" x="-99" y="-186"/><int name="delay" value="130"/><string name="_hash" value="d9cecbf431679ca06ee6457ddcb7121ed25de20ee468cbedd1ffbf9eb1369616"/></canvas><canvas name="9" width="68" height="70"><vector name="origin" x="-109" y="-188"/><int name="delay" value="130"/><string name="_hash" value="56dd304208b1f3e1baa739d3362005a212048423c2f4efd314b352bd67010e38"/></canvas><uol name="10" value="6"/><uol name="11" value="7"/><uol name="12" value="8"/><uol name="13" value="9"/><uol name="14" value="6"/><uol name="15" value="7"/><uol name="16" value="8"/><uol name="17" value="9"/><uol name="18" value="6"/><uol name="19" value="7"/><uol name="20" value="8"/><uol name="21" value="9"/><uol name="22" value="6"/><uol name="23" value="7"/><uol name="24" value="8"/><uol name="25" value="9"/></imgdir></imgdir><imgdir name="5"><imgdir name="info"><string name="answer" value="艺术体操"/></imgdir><imgdir name="ani"><canvas name="0" width="126" height="78"><vector name="origin" x="-53" y="-160"/><int name="delay" value="150"/><string name="_hash" value="2b9579ecc8cd5c006a1a92ef8e3337339baf765342183606c8ab79fa9eb1674b"/></canvas><canvas name="1" width="110" height="82"><vector name="origin" x="-69" y="-155"/><int name="delay" value="150"/><string name="_hash" value="a4c9d355d0d7c7fe2db2e39af886b0405b73d0a1428ce9e2b62bd1c9229b1c8e"/></canvas><canvas name="2" width="118" height="86"><vector name="origin" x="-61" y="-152"/><int name="delay" value="150"/><string name="_hash" value="a8539054627296f1d7b09efa1253bc5f9ed486d81c895d174eadb5e53d6d8e1e"/></canvas><canvas name="3" width="116" height="75"><vector name="origin" x="-63" y="-164"/><int name="delay" value="150"/><string name="_hash" value="095536af5429405972ca4389a3567456de55f51f4497867de7ba9f926f21a6c5"/></canvas></imgdir></imgdir><imgdir name="6"><imgdir name="info"><string name="answer" value="羽毛球"/></imgdir><imgdir name="ani"><canvas name="0" width="72" height="56"><vector name="origin" x="-114" y="-198"/><int name="delay" value="130"/><string name="_hash" value="9384d840b5c99fcaa9512556331b7d6052e0ae195656e1813b80e89ac06035f4"/></canvas><canvas name="1" width="70" height="56"><vector name="origin" x="-116" y="-198"/><int name="delay" value="130"/><string name="_hash" value="ecc7fb3f3f4a77eac9d70df92b0a63d6a3b932b0c17be1f0c9a733442d55ad06"/></canvas><canvas name="2" width="72" height="56"><vector name="origin" x="-118" y="-198"/><int name="delay" value="130"/><string name="_hash" value="9a6a78ade8de67ef0cf3ea137e94d714a69e45270408e7256cee1a43bb476911"/></canvas><canvas name="3" width="1" height="1"><vector name="origin" x="-121" y="-198"/><int name="delay" value="130"/><string name="_inlink" value="BeijingOlympic/AniQuiz/6/ani/1"/></canvas><canvas name="4" width="135" height="128"><vector name="origin" x="-60" y="-126"/><int name="delay" value="130"/><string name="_hash" value="d5c16738b3c48222e494b7ca7fa22dc423c41a21863029cfcfb10feaef1b68c9"/></canvas><canvas name="5" width="85" height="137"><vector name="origin" x="-104" y="-112"/><int name="delay" value="130"/><string name="_hash" value="38d8cadea4870bc5b56953b4244429a5a324a05abb6111c21ca96b2d19c9c410"/></canvas><canvas name="6" width="58" height="115"><vector name="origin" x="-132" y="-132"/><int name="delay" value="130"/><string name="_hash" value="c1057058fffe65dfaec4822bb1367cbe3e28b37d0f6ac08f425a70cd47ba3adf"/></canvas><canvas name="7" width="86" height="82"><vector name="origin" x="-133" y="-168"/><int name="delay" value="130"/><string name="_hash" value="e467855e05caf62d018628bbb54f56c14c58516cca86244204e62bd60eda59d7"/></canvas><canvas name="8" width="61" height="104"><vector name="origin" x="-125" y="-160"/><int name="delay" value="130"/><string name="_hash" value="15ec22f3db04450b59dfba84cebbadc0a291c0e598f92e4411994c81c6587c72"/></canvas><canvas name="9" width="120" height="138"><vector name="origin" x="-63" y="-123"/><int name="delay" value="130"/><string name="_hash" value="a8f5c875aeb8dae3e42a87e174ab91110cf2f3be5373623a6cd2cc21f86f91a2"/></canvas><canvas name="10" width="1" height="1"><vector name="origin" x="-125" y="-198"/><int name="delay" value="130"/><string name="_inlink" value="BeijingOlympic/AniQuiz/6/ani/2"/></canvas><canvas name="11" width="1" height="1"><vector name="origin" x="-121" y="-198"/><int name="delay" value="130"/><string name="_inlink" value="BeijingOlympic/AniQuiz/6/ani/1"/></canvas><canvas name="12" width="1" height="1"><vector name="origin" x="-118" y="-198"/><int name="delay" value="130"/><string name="_inlink" value="BeijingOlympic/AniQuiz/6/ani/2"/></canvas><canvas name="13" width="1" height="1"><vector name="origin" x="-116" y="-198"/><int name="delay" value="130"/><string name="_inlink" value="BeijingOlympic/AniQuiz/6/ani/1"/></canvas></imgdir></imgdir><imgdir name="7"><imgdir name="info"><string name="answer" value="棒球"/></imgdir><imgdir name="ani"><canvas name="0" width="60" height="63"><vector name="origin" x="-109" y="-191"/><int name="delay" value="150"/><string name="_hash" value="2b1538664b811a7e2df59fa5912197166bb6f99c127aa0043a9be94171581a5b"/></canvas><canvas name="1" width="1" height="1"><vector name="origin" x="-109" y="-191"/><int name="delay" value="150"/><string name="_inlink" value="BeijingOlympic/AniQuiz/7/ani/0"/></canvas><canvas name="2" width="129" height="63"><vector name="origin" x="-40" y="-191"/><int name="delay" value="150"/><string name="_hash" value="610e2e437556ee252b7da10de9899ed8297a6f2c959f11fa09794ed9694690e0"/></canvas><canvas name="3" width="71" height="63"><vector name="origin" x="-98" y="-191"/><int name="delay" value="150"/><string name="_hash" value="2eec206411e105235e1c374ca46f8139fe62e1686250f9fe29a299108ee902f5"/></canvas><canvas name="4" width="101" height="65"><vector name="origin" x="-113" y="-189"/><int name="delay" value="150"/><string name="_hash" value="240028e9a353260517ca201cfcb1616788bb502b112c324a3c685884fd00fef4"/></canvas><canvas name="5" width="71" height="79"><vector name="origin" x="-98" y="-188"/><int name="delay" value="150"/><string name="_hash" value="c80227de903b6be4dbefa1cfb33c90cdf5abc247cecb331b879472caa0406e35"/></canvas><canvas name="6" width="76" height="73"><vector name="origin" x="-92" y="-185"/><int name="delay" value="150"/><string name="_hash" value="6851c0db717f7ae942768a3ad10c84eab4ab0a0c19402deb7217cf328d6b12ad"/></canvas><canvas name="7" width="74" height="73"><vector name="origin" x="-92" y="-185"/><int name="delay" value="150"/><string name="_hash" value="632b52385cfa6541928a0bcb6b849f530c682f3ce22741017fcbe87870bec411"/></canvas><canvas name="8" width="70" height="73"><vector name="origin" x="-96" y="-185"/><int name="delay" value="150"/><string name="_hash" value="82f62461742ac330db8753a861f4ba1ccd6ebccb93b01726a8bb681259833d28"/></canvas><canvas name="9" width="71" height="73"><vector name="origin" x="-95" y="-185"/><int name="delay" value="150"/><string name="_hash" value="a605df187a558de35df8f4bd18aecc86c0d8ec82f531f15ba606cc33eb3e2ed4"/></canvas><canvas name="10" width="56" height="73"><vector name="origin" x="-113" y="-185"/><int name="delay" value="150"/><string name="_hash" value="b8548cd1714e0fe505fa53fe2a02cfe099f715a8b1f608610248d919ae7b74dc"/></canvas><canvas name="11" width="56" height="73"><vector name="origin" x="-113" y="-185"/><int name="delay" value="150"/><string name="_hash" value="470ded3c33f9b25e201c9082891cbb066046e8bf068e30b84a324ab7163e2358"/></canvas><canvas name="12" width="56" height="73"><vector name="origin" x="-113" y="-185"/><int name="delay" value="150"/><string name="_hash" value="ac50128c9779eb2d1a7d5eed535ff8f3bf6607f5fa90dbe125c78d5d02499f96"/></canvas><canvas name="13" width="56" height="73"><vector name="origin" x="-113" y="-185"/><int name="delay" value="150"/><string name="_hash" value="3b44be145ef79f44e4994cde414db50d728daa38c6ee7f2e798191624d4965ed"/></canvas><canvas name="14" width="53" height="73"><vector name="origin" x="-113" y="-185"/><int name="delay" value="150"/><string name="_hash" value="12b270116e6a86efd6d78d8b3998a1793eb16f356a94dc765cd4fd2a5f1d053b"/></canvas></imgdir></imgdir><imgdir name="8"><imgdir name="info"><string name="answer" value="射击"/></imgdir><imgdir name="ani"><canvas name="0" width="108" height="75"><vector name="origin" x="-73" y="-198"/><int name="delay" value="150"/><string name="_hash" value="ea4dd4336783241b3a4747aad13afec47f9fd56bd960b5dd3491563a14fb9c96"/></canvas><canvas name="1" width="108" height="70"><vector name="origin" x="-74" y="-200"/><int name="delay" value="150"/><string name="_hash" value="56250ca5be01cdd7f980cc783435267ddab9a7c7c31874f77e017d4f80cdc968"/></canvas><canvas name="2" width="107" height="69"><vector name="origin" x="-75" y="-200"/><int name="delay" value="150"/><string name="_hash" value="d775243496a5bca1fa3e73c7fa8e8542ab2869f640d07d8866b70425e40df30a"/></canvas><canvas name="3" width="95" height="59"><vector name="origin" x="-88" y="-200"/><int name="delay" value="150"/><string name="_hash" value="1fbad57b7046d45373bf5ef65a5dfc34c0ebd45a64e6b78a9aed33a68ba4da6f"/></canvas><canvas name="4" width="97" height="55"><vector name="origin" x="-87" y="-199"/><int name="delay" value="150"/><string name="_hash" value="4e53df7fcec5e9992d439a64861bed26a04b592233283194988c1a73a0505aec"/></canvas><canvas name="5" width="119" height="57"><vector name="origin" x="-64" y="-197"/><int name="delay" value="150"/><string name="_hash" value="3722dbb38020bbb7a62cdb3297fab9d5f51fd849b134ab64ba72c972046a56ef"/></canvas><canvas name="6" width="147" height="53"><vector name="origin" x="-35" y="-203"/><int name="delay" value="150"/><string name="_hash" value="0829afd364f752e7aae2dde167895f9c42cf9e553a95c5c61fd86fd7b197a5d3"/></canvas><canvas name="7" width="159" height="56"><vector name="origin" x="-22" y="-198"/><int name="z" value="0"/><int name="delay" value="150"/><string name="_hash" value="ad3ddf04e3aef5940affdb613fa2be41ed9e189639eea6a102044e421d1ee7ef"/></canvas><canvas name="8" width="76" height="54"><vector name="origin" x="-106" y="-200"/><int name="z" value="0"/><int name="delay" value="150"/><string name="_hash" value="825f4fa4529c67a1cf95e138fedb32d9db592120fe7b05989fe54a31b9d26fd5"/></canvas><canvas name="9" width="75" height="54"><vector name="origin" x="-107" y="-200"/><int name="z" value="0"/><int name="delay" value="150"/><string name="_hash" value="28511eeca6524cca95ade2c6dc8ac856d01d0a6f83d4ac14378e8bef94454825"/></canvas><canvas name="10" width="75" height="54"><vector name="origin" x="-108" y="-200"/><int name="z" value="0"/><int name="delay" value="150"/><string name="_hash" value="ca0bfd1bab34120c053460b8f6c8d43566a4ada8e93194695ccec48d10a4bd3f"/></canvas><canvas name="11" width="74" height="55"><vector name="origin" x="-109" y="-199"/><int name="z" value="0"/><int name="delay" value="150"/><string name="_hash" value="fdf4acc102676ceb163204bb6a315453cf4be3a3dd53ab56798891eaf180c362"/></canvas><canvas name="12" width="77" height="57"><vector name="origin" x="-106" y="-197"/><int name="z" value="0"/><int name="delay" value="150"/><string name="_hash" value="687b05565f5332327a3cf43c229bb813cecf0c93c997598fd3f626c002c703ed"/></canvas><canvas name="13" width="78" height="51"><vector name="origin" x="-104" y="-203"/><int name="z" value="0"/><int name="delay" value="150"/><string name="_hash" value="e27eb654843f58330072612ab32d8aa66903a2eb35e0cc5ecd81b5002915f651"/></canvas></imgdir></imgdir><canvas name="Question" width="244" height="37"><vector name="origin" x="0" y="0"/><string name="_hash" value="e96678bc562632edd2c49704fe78bce7f301f05f27e6d4b58f104ad95302d1b9"/></canvas><imgdir name="9"><imgdir name="info"><string name="answer" value="射箭"/></imgdir><imgdir name="ani"><canvas name="0" width="76" height="83"><vector name="origin" x="-110" y="-178"/><int name="delay" value="120"/><string name="_hash" value="b4606451198a83b0dc662379c2d1e07138730c8b74c7eb711ef00e0551107afa"/></canvas><canvas name="1" width="76" height="84"><vector name="origin" x="-111" y="-177"/><int name="delay" value="120"/><string name="_hash" value="a645b56906ab915aa686d9871a88497bbb84d78f6d2dd20e984be87e5a681fe9"/></canvas><canvas name="2" width="76" height="84"><vector name="origin" x="-112" y="-177"/><int name="delay" value="120"/><string name="_hash" value="c5f891caa58c98b408435282a97c9e664ee48a3de5011637d4fb682f5df645d8"/></canvas><canvas name="3" width="76" height="84"><vector name="origin" x="-111" y="-177"/><int name="delay" value="120"/><string name="_hash" value="24a92a44b53c933f97bd3ca22644983e1484d3580c2df0bac11148f79aed4399"/></canvas><canvas name="4" width="76" height="85"><vector name="origin" x="-110" y="-176"/><int name="delay" value="120"/><string name="_hash" value="b495f26bd05de04737fbdb52361af976d538c09df6bbc6a685e49999b39f0305"/></canvas><canvas name="5" width="99" height="86"><vector name="origin" x="-94" y="-166"/><int name="delay" value="120"/><string name="_hash" value="31a5e61eea4c670326fa87f494f3d01ce169992fd68eab9a4b4643adf128b10e"/></canvas><canvas name="6" width="88" height="83"><vector name="origin" x="-103" y="-167"/><int name="delay" value="120"/><string name="_hash" value="f48ee966e598ba7ef43cb1c16e9660505f7d09da4461949c60ad2f34957a9a95"/></canvas><canvas name="7" width="80" height="83"><vector name="origin" x="-112" y="-166"/><int name="delay" value="120"/><string name="_hash" value="e2fd9d00b73ce70a248fad22c1c88a9cb8b4efc044856c106577c7de4c1695a1"/></canvas><canvas name="8" width="80" height="84"><vector name="origin" x="-113" y="-168"/><int name="delay" value="120"/><string name="_hash" value="c921bf09482e8e28eeddd247a33bcfbd32236305bdece4d04f4614c14d4c8acc"/></canvas><canvas name="9" width="80" height="84"><vector name="origin" x="-114" y="-172"/><int name="delay" value="120"/><string name="_hash" value="efcc298d01cb56118ce615aed3ddb8afe4e85f2d95c12d070f8a25bf277b4567"/></canvas><canvas name="10" width="76" height="84"><vector name="origin" x="-118" y="-173"/><int name="delay" value="120"/><string name="_hash" value="3ff845cf9ac5b6f0e1f8d485ab8f63469ed06cb8222e19d44041a3ae8c097ac5"/></canvas></imgdir></imgdir><imgdir name="10"><imgdir name="info"><string name="answer" value="足球"/></imgdir><imgdir name="ani"><canvas name="0" width="113" height="50"><vector name="origin" x="-83" y="-210"/><int name="delay" value="130"/><string name="_hash" value="f77794b413eec0f6b506f2184b43b7b0a7ff19ebfe6f528772ff8ab0b7da1416"/></canvas><canvas name="1" width="94" height="53"><vector name="origin" x="-100" y="-210"/><int name="delay" value="130"/><string name="_hash" value="4183c79cf58b7c338fd0915e1910ba9e417ee77a79f75e588dce2560121c716c"/></canvas><canvas name="2" width="77" height="49"><vector name="origin" x="-119" y="-210"/><int name="delay" value="130"/><string name="_hash" value="e5bd76e35e67c495463c286808d2e2522130e91687946800d7b6c7a01a53bd8b"/></canvas><canvas name="3" width="100" height="49"><vector name="origin" x="-94" y="-210"/><int name="delay" value="130"/><string name="_hash" value="c68bbbb93eab13f051003dcc83efcf6f155a9a02145ba458af6bf0789892022b"/></canvas></imgdir></imgdir><imgdir name="11"><imgdir name="info"><string name="answer" value="桌球"/></imgdir><imgdir name="ani"><canvas name="0" width="133" height="80"><vector name="origin" x="-71" y="-180"/><int name="delay" value="120"/><string name="_hash" value="66c10d6c3cae59561c100240856d0290ff1b6dd6df788874f9bec01f9715a2ac"/></canvas><canvas name="1" width="121" height="80"><vector name="origin" x="-79" y="-180"/><int name="delay" value="120"/><string name="_hash" value="9b86f488542c725688ce8ca5e31aedfcbe4e016138472dc0179d21f6027a5acf"/></canvas><canvas name="2" width="96" height="80"><vector name="origin" x="-100" y="-180"/><int name="delay" value="120"/><string name="_hash" value="3b3ea3b1b70bba3affa795f9bf699bc7df4bf33d006866044d5c453d3a648e54"/></canvas><canvas name="3" width="78" height="80"><vector name="origin" x="-113" y="-180"/><int name="delay" value="120"/><string name="_hash" value="d6197def9457976a4a2478958882ada4afef04ea8cc11f2e128313e9a935187d"/></canvas><canvas name="4" width="120" height="80"><vector name="origin" x="-80" y="-180"/><int name="delay" value="120"/><string name="_hash" value="af9b5fc2e3c6f9657c1c48bf8a14628b9c85b27ace806e2f8812dea568accbbb"/></canvas></imgdir></imgdir><imgdir name="12"><imgdir name="info"><string name="answer" value="手球"/></imgdir><imgdir name="ani"><canvas name="0" width="70" height="63"><vector name="origin" x="-108" y="-195"/><int name="delay" value="120"/><string name="_hash" value="f1912b05316294ff358d31dc4712c5880d16c025b6d57ce1bf0974df07fda56a"/></canvas><canvas name="1" width="70" height="62"><vector name="origin" x="-109" y="-196"/><int name="delay" value="120"/><string name="_hash" value="07690f3d0999a392c0be3a4689d155e15338ca2d7dda06748f3416563fe5c03a"/></canvas><canvas name="2" width="69" height="61"><vector name="origin" x="-111" y="-197"/><int name="delay" value="120"/><string name="_hash" value="1c61fbdd295fe80c9fb8c3495d5e66b1da8ae655f1bfc02aa2a661e25b684531"/></canvas><canvas name="3" width="67" height="63"><vector name="origin" x="-112" y="-195"/><int name="delay" value="120"/><string name="_hash" value="3a3cd916f90a1ac8ff81f55d4e187059bab44c997ba5024ae7ecebd08960a7a8"/></canvas><canvas name="4" width="70" height="64"><vector name="origin" x="-110" y="-194"/><int name="delay" value="120"/><string name="_hash" value="a919bd8c69add92f561a0d7e34ddeeb54c15bcb1c197fcf982e08dcffcff1900"/></canvas><canvas name="5" width="70" height="65"><vector name="origin" x="-108" y="-193"/><int name="delay" value="120"/><string name="_hash" value="22fa9ff793dc6c324f7f9064c0a074f44b6a24c222952d82d22283aa89c566e6"/></canvas><canvas name="6" width="1" height="1"><vector name="origin" x="-108" y="-195"/><int name="delay" value="120"/><string name="_inlink" value="BeijingOlympic/AniQuiz/12/ani/0"/></canvas><canvas name="7" width="1" height="1"><vector name="origin" x="-109" y="-196"/><int name="delay" value="120"/><string name="_inlink" value="BeijingOlympic/AniQuiz/12/ani/1"/></canvas><canvas name="8" width="1" height="1"><vector name="origin" x="-111" y="-197"/><int name="delay" value="120"/><string name="_inlink" value="BeijingOlympic/AniQuiz/12/ani/2"/></canvas><canvas name="9" width="1" height="1"><vector name="origin" x="-112" y="-195"/><int name="delay" value="120"/><string name="_inlink" value="BeijingOlympic/AniQuiz/12/ani/3"/></canvas><canvas name="10" width="1" height="1"><vector name="origin" x="-110" y="-194"/><int name="delay" value="120"/><string name="_inlink" value="BeijingOlympic/AniQuiz/12/ani/4"/></canvas><canvas name="11" width="1" height="1"><vector name="origin" x="-108" y="-193"/><int name="delay" value="120"/><string name="_inlink" value="BeijingOlympic/AniQuiz/12/ani/5"/></canvas><canvas name="12" width="70" height="63"><vector name="origin" x="-108" y="-195"/><int name="delay" value="120"/><string name="_hash" value="92f82fc4257e71ede25899059a5c33f71971de0de42af4a99861b745a2331438"/></canvas><canvas name="13" width="74" height="69"><vector name="origin" x="-105" y="-188"/><int name="delay" value="120"/><string name="_hash" value="ac1857a6ed5abc8fff17b4148854a6bfb275922782e2aeac92a11b5b8e731238"/></canvas><canvas name="14" width="115" height="63"><vector name="origin" x="-61" y="-191"/><int name="delay" value="120"/><string name="_hash" value="9c297efe4120d2cb33cfbc4880852684394c7ece827a5dccae3e6e8993eaa7f8"/></canvas><canvas name="15" width="155" height="58"><vector name="origin" x="-22" y="-204"/><int name="delay" value="120"/><string name="_hash" value="baf0aad5ec802ac782716f2a376572ee7b20ed8e0796d2e51382905c21ebd833"/></canvas><canvas name="16" width="123" height="63"><vector name="origin" x="-54" y="-195"/><int name="delay" value="120"/><string name="_hash" value="bee11890bb826d16f96ec93671dadf7d0271309e868b0e7487ed3fe4bb9b09b9"/></canvas><canvas name="17" width="83" height="64"><vector name="origin" x="-95" y="-194"/><int name="delay" value="120"/><string name="_hash" value="705af4420e572113c3aebb50536e4f5297764ecaa519bb2d7f4163a55b6981ef"/></canvas><canvas name="18" width="72" height="65"><vector name="origin" x="-106" y="-193"/><int name="delay" value="120"/><string name="_hash" value="227498e1b78e77eb4724d9a0ec8bd2928aae395c506de5ca4d222cc1cc6a5ce9"/></canvas></imgdir></imgdir><imgdir name="13"><imgdir name="info"><string name="answer" value="篮球"/></imgdir><imgdir name="ani"><canvas name="0" width="64" height="77"><vector name="origin" x="-114" y="-186"/><int name="delay" value="110"/><string name="_hash" value="f78f878dfa07ed6b63bbf0c7abfcec1a47b6b16a81bcbf18491dc14a31fb521d"/></canvas><canvas name="1" width="63" height="76"><vector name="origin" x="-113" y="-188"/><int name="delay" value="110"/><string name="_hash" value="c873e9aae25a5074b899124c0a69c603f6aba2cc67df9f201185d529ac202887"/></canvas><canvas name="2" width="62" height="74"><vector name="origin" x="-111" y="-189"/><int name="delay" value="110"/><string name="_hash" value="2db6db92efca242fce345dcdeccbe08a91be7d530afe62383359c2788c467e85"/></canvas><canvas name="3" width="63" height="76"><vector name="origin" x="-112" y="-187"/><int name="delay" value="110"/><string name="_hash" value="8f7f65635bbcd1b33bcb8bcf4fdb94864181c75fc2726805c81c759f20c4d810"/></canvas><canvas name="4" width="63" height="77"><vector name="origin" x="-113" y="-185"/><int name="delay" value="110"/><string name="_hash" value="30f9a5832caaa04f3dc98101aeb5ba53773f6d4be4acab3f4a2287297c274917"/></canvas></imgdir></imgdir><imgdir name="14"><imgdir name="info"><string name="answer" value="拳击"/></imgdir><imgdir name="ani"><canvas name="0" width="77" height="55"><vector name="origin" x="-104" y="-204"/><int name="delay" value="120"/><string name="_hash" value="4a123051c32cbd85e9226643478e86fc90c12670a8e589f1f22d6f896e88d186"/></canvas><canvas name="1" width="78" height="57"><vector name="origin" x="-104" y="-203"/><int name="delay" value="120"/><string name="_hash" value="5bb955861c1934761610bc3a2ec8cdedecb8c97553cdb708c1906e160410a0c6"/></canvas><canvas name="2" width="80" height="59"><vector name="origin" x="-103" y="-202"/><int name="delay" value="120"/><string name="_hash" value="c0c8ca237c6f1129aab418d08c9562499ab7fa4d2adcd160d492e2d281af6e56"/></canvas><canvas name="3" width="82" height="61"><vector name="origin" x="-102" y="-201"/><int name="delay" value="120"/><string name="_hash" value="9b3fbfd34fc62970d90e5c6940e93e84ca7f9d895517352b142bdf8552578507"/></canvas><canvas name="4" width="80" height="59"><vector name="origin" x="-103" y="-202"/><int name="delay" value="120"/><string name="_hash" value="c37cbfc04eefb163b6f7aab0be2e938fb7e303dde491dcd01908826e09779ea6"/></canvas><canvas name="5" width="78" height="57"><vector name="origin" x="-104" y="-203"/><int name="delay" value="120"/><string name="_hash" value="e5b0a7cf980e7bc12997ace0ce8cc29d6543b90d5074a3872c63290edcc9dea8"/></canvas><canvas name="6" width="75" height="55"><vector name="origin" x="-106" y="-204"/><int name="delay" value="120"/><string name="_hash" value="0de5f5f5506cd26f2455fcca934992f6185cf6b866fcc21f5f64a023f33267d3"/></canvas><canvas name="7" width="88" height="55"><vector name="origin" x="-92" y="-204"/><int name="delay" value="120"/><string name="_hash" value="7a4d0c2fc35d122266b420e2b822ab80b8915fce54a33e358a05e8788c6fefdf"/></canvas><canvas name="8" width="79" height="55"><vector name="origin" x="-102" y="-204"/><int name="delay" value="120"/><string name="_hash" value="aa1edb7234820914e9bc469e90a7909c69b0d8c1955a85b789a5024a06afee79"/></canvas><canvas name="9" width="1" height="1"><vector name="origin" x="-92" y="-204"/><int name="delay" value="120"/><string name="_inlink" value="BeijingOlympic/AniQuiz/14/ani/7"/></canvas><canvas name="10" width="1" height="1"><vector name="origin" x="-102" y="-204"/><int name="delay" value="120"/><string name="_inlink" value="BeijingOlympic/AniQuiz/14/ani/8"/></canvas><canvas name="11" width="1" height="1"><vector name="origin" x="-92" y="-204"/><int name="delay" value="120"/><string name="_inlink" value="BeijingOlympic/AniQuiz/14/ani/7"/></canvas><canvas name="12" width="1" height="1"><vector name="origin" x="-102" y="-204"/><int name="delay" value="120"/><string name="_inlink" value="BeijingOlympic/AniQuiz/14/ani/8"/></canvas></imgdir></imgdir></imgdir><imgdir name="TextQuiz"><imgdir name="0"><imgdir name="info"><string name="answer" value="贝贝、晶晶、欢欢、迎迎、妮妮"/><string name="question" value="北京二○○八年第二十九届奥运会吉祥物的名字分别是（）."/></imgdir></imgdir><imgdir name="1"><imgdir name="info"><string name="answer" value="同一个世界，同一个梦想"/><string name="question" value="2008北京奥运会的口号是（）．"/></imgdir></imgdir><imgdir name="2"><imgdir name="info"><string name="answer" value="希腊雅典"/><string name="question" value="（）是奥林匹克运动的发源地."/></imgdir></imgdir><imgdir name="3"><imgdir name="info"><string name="answer" value="29界"/><string name="question" value="2008北京奥运会是第（）届奥运会."/></imgdir></imgdir><imgdir name="4"><imgdir name="info"><string name="answer" value="奥运五环"/><string name="question" value="奥林匹克标志是（）．"/></imgdir></imgdir><imgdir name="5"><imgdir name="info"><string name="answer" value="IOC"/><string name="question" value="主管奥运会的国际机构叫（）. （请用英文缩写回答．）"/></imgdir></imgdir><imgdir name="6"><imgdir name="info"><string name="answer" value="26个"/><string name="question" value="奥运会中田径项目总共为（）个."/></imgdir></imgdir><imgdir name="7"><imgdir name="info"><string name="answer" value="许海峰"/><string name="question" value="中国第一块奥运会金牌获得者是（）．"/></imgdir></imgdir><imgdir name="8"><imgdir name="info"><string name="answer" value="0623"/><string name="question" value="（）是奥林匹克日．(请输入mmdd格式。)"/></imgdir></imgdir><imgdir name="9"><imgdir name="info"><string name="answer" value="游泳"/><string name="question" value=" 中国赢得奥运奖牌最多的是（）队．"/></imgdir></imgdir><imgdir name="10"><imgdir name="info"><string name="answer" value="2004雅典"/><string name="question" value="（）奥运会的火炬传递是奥运圣火历史上的首次环球传递．"/></imgdir></imgdir><imgdir name="11"><imgdir name="info"><string name="answer" value="５大陆"/><string name="question" value="奥运五环中五环代表的意思是 ( )."/></imgdir></imgdir><imgdir name="12"><imgdir name="info"><string name="answer" value="3"/><string name="question" value="现代奥运会是从第（）届开始设立金牌的．"/></imgdir></imgdir><imgdir name="13"><imgdir name="info"><string name="answer" value="330"/><string name="question" value="北京奥运会有（）个比赛项目．"/></imgdir></imgdir><imgdir name="14"><imgdir name="info"><string name="answer" value="美国"/><string name="question" value="举办现代奥运会次数最多的国家是（）．"/></imgdir></imgdir><imgdir name="15"><imgdir name="info"><string name="answer" value="瑞士洛桑"/><string name="question" value="国际奥委会总部设在（）．"/></imgdir></imgdir><imgdir name="16"><imgdir name="info"><string name="answer" value="伊菲图斯"/><string name="question" value="古代奥运会创始人是（）．"/></imgdir></imgdir><canvas name="Question" width="244" height="37"><vector name="origin" x="0" y="0"/><string name="_hash" value="d2fb85597cb865889adb6887a74c81c66b50476c2d49ae746caee0fa5d3f04b0"/></canvas></imgdir><string name="path" value="UI/UIWindow.img/BeijingOlympicQuiz"/></imgdir></imgdir>